[
  {
    "title": "De Dammen 29",
    "price": 285000,
    "address": "8701 ZN Bolsward (Bolsward-Noordoost)",
    "size": 50.0,
    "energy_label": "Onbekend",
    "garden_terrace": "Nee",
    "image_url": "https://casco-media-prod.global.ssl.fastly.net/9e6dd170-3257-5e7f-8ae0-63903ccd5c46/2ca5a4ac70e59104f2dfceedf1f90ce1.jpg?width=600&auto=webp",
    "link": "https://www.pararius.nl/huis-te-koop/bolsward/9e6dd170/de-dammen",
    "provider": "Pararius",
    "date_scraped": "2026-01-10"
  },
  {
    "title": "De Diken 4",
    "price": 325000,
    "address": "8701 GM Bolsward (Bolsward-Noordoost)",
    "size": 50.0,
    "energy_label": "Onbekend",
    "garden_terrace": "Nee",
    "image_url": "https://casco-media-prod.global.ssl.fastly.net/9dddbc97-2201-5588-8f08-e8c054fb97e7/4669ec02e4016a87a4375ab1bb5b3556.jpg?width=600&auto=webp",
    "link": "https://www.pararius.nl/huis-te-koop/bolsward/9dddbc97/de-diken",
    "provider": "Pararius",
    "date_scraped": "2026-01-10"
  },
  {
    "title": "Kennedylaan",
    "price": 429000,
    "address": "5688 CN Oirschot (Oirschot-Centrum)",
    "size": 50.0,
    "energy_label": "Onbekend",
    "garden_terrace": "Nee",
    "image_url": "https://casco-media-prod.global.ssl.fastly.net/listings/api/media/1e9d3256-e382-5e97-9d6e-e30ede8c7cc1/c5bb6c5b-da36-51cf-938d-4d90464c7754?original_uri=https%3A%2F%2Fimages.realworks.nl%2Fservlets%2Fimages%2Fmedia.objectmedia%2F259287756.webp%3Fcheck%3Dsha256%253A5af4ecda6419c9230b494f144fd0b3e569958c856fe2d681d23bfd47c26e58e3%26resize%3D4%26selected%3D259287756%23foto259287756?sig=a1489722c737f59008a98c499f74733639fea71802a25b41af95c1d350cdc462&width=600&auto=webp",
    "link": "https://www.pararius.nl/huis-te-koop/oirschot/1e9d3256/kennedylaan",
    "provider": "Pararius",
    "date_scraped": "2026-01-10"
  },
  {
    "title": "Theo Mann-Bouwmeesterstraat 82",
    "price": 435000,
    "address": "3207 VM Spijkenisse (Maaswijk-Noordoost)",
    "size": 50.0,
    "energy_label": "Onbekend",
    "garden_terrace": "Nee",
    "image_url": "https://casco-media-prod.global.ssl.fastly.net/653ce8d3-50ee-5192-954c-b513e14cc2a7/03ae1545ab761bee13b329b4e74de172.jpg?width=600&auto=webp",
    "link": "https://www.pararius.nl/appartement-te-koop/spijkenisse/653ce8d3/theo-mann-bouwmeesterstraat",
    "provider": "Pararius",
    "date_scraped": "2026-01-10"
  },
  {
    "title": "Sambastraat 6",
    "price": 450000,
    "address": "7323 SV Apeldoorn (Zuidbroek - Mozaïek & Rooster)",
    "size": 50.0,
    "energy_label": "Onbekend",
    "garden_terrace": "Nee",
    "image_url": "https://casco-media-prod.global.ssl.fastly.net/e60db96a-bbb6-56aa-b030-be891e3d5156/4083155bdb63fd1b06457545e9d12d13.jpg?width=600&auto=webp",
    "link": "https://www.pararius.nl/huis-te-koop/apeldoorn/e60db96a/sambastraat",
    "provider": "Pararius",
    "date_scraped": "2026-01-10"
  },
  {
    "title": "Grupellostraat",
    "price": 349000,
    "address": "6461 EV Kerkrade (Kerkrade-Centrum)",
    "size": 50.0,
    "energy_label": "Onbekend",
    "garden_terrace": "Nee",
    "image_url": "https://casco-media-prod.global.ssl.fastly.net/listings/api/media/83f45c72-9cde-5175-b145-f49a79b2162d/0b685783-1ba5-5aec-b28f-b057f1ced561?original_uri=https%3A%2F%2Fimages.realworks.nl%2Fservlets%2Fimages%2Fmedia.objectmedia%2F258442992.webp%3Fcheck%3Dsha256%253A664a3154e842978f0fb1bc9547db0e2c4b65f1c0480b7092435d1bb2e9186da3%26resize%3D4%26selected%3D258442992%23foto258442992?sig=4476cd94bad608bae3fd97c54ff353338d39923ce36826423cc22e9ebbba59be&width=600&auto=webp",
    "link": "https://www.pararius.nl/huis-te-koop/kerkrade/83f45c72/grupellostraat",
    "provider": "Pararius",
    "date_scraped": "2026-01-10"
  },
  {
    "title": "Lelystraat",
    "price": 325000,
    "address": "8265 BD Kampen (Flevowijk)",
    "size": 50.0,
    "energy_label": "Onbekend",
    "garden_terrace": "Nee",
    "image_url": "https://casco-media-prod.global.ssl.fastly.net/listings/api/media/d9784ba1-76d8-5c93-9d76-3d2e7f445499/cf23a519-0e65-5806-98e9-971ef070c772?original_uri=https%3A%2F%2Fimages.realworks.nl%2Fservlets%2Fimages%2Fmedia.objectmedia%2F259236986.webp%3Fcheck%3Dsha256%253A55ef62e6961777ed5ba99530247c84383d81a07c1ad82cce0427e31e2459903d%26resize%3D4%26selected%3D259236986%23foto259236986?sig=f765d83547ba04d5cfe1de201e778636a71497d9a39ad4cdaf856b0d9e4f6fbb&width=600&auto=webp",
    "link": "https://www.pararius.nl/huis-te-koop/kampen/d9784ba1/lelystraat",
    "provider": "Pararius",
    "date_scraped": "2026-01-10"
  },
  {
    "title": "De Singel 32",
    "price": 249000,
    "address": "9203 ZA Drachten (De Bouwen)",
    "size": 50.0,
    "energy_label": "Onbekend",
    "garden_terrace": "Nee",
    "image_url": "https://casco-media-prod.global.ssl.fastly.net/e5d62942-0cff-5663-a7a7-3a2297994f60/f11c132a06b305028862619f4fd3280c.jpg?width=600&auto=webp",
    "link": "https://www.pararius.nl/huis-te-koop/drachten/e5d62942/de-singel",
    "provider": "Pararius",
    "date_scraped": "2026-01-10"
  },
  {
    "title": "Patrijsstraat 35",
    "price": 379500,
    "address": "1826 KN Alkmaar (De Horn-Noord)",
    "size": 50.0,
    "energy_label": "Onbekend",
    "garden_terrace": "Nee",
    "image_url": "https://casco-media-prod.global.ssl.fastly.net/8620d3bf-03e3-55fa-9175-7f5cc3e39271/7d429c300504f2609d1a87d5e1c4b615.jpg?width=600&auto=webp",
    "link": "https://www.pararius.nl/huis-te-koop/alkmaar/8620d3bf/patrijsstraat",
    "provider": "Pararius",
    "date_scraped": "2026-01-10"
  },
  {
    "title": "Lavendelstraat",
    "price": 400000,
    "address": "6641 BW Beuningen Gld (Beuningen-Centrum Oost)",
    "size": 50.0,
    "energy_label": "Onbekend",
    "garden_terrace": "Nee",
    "image_url": "https://casco-media-prod.global.ssl.fastly.net/listings/api/media/a97ad3a6-e51f-511e-9255-78354dfd1b1c/7777a94e-354a-5cdf-b570-3d375fdcdfcf?original_uri=https%3A%2F%2Fimages.realworks.nl%2Fservlets%2Fimages%2Fmedia.objectmedia%2F255403888.webp%3Fcheck%3Dsha256%253Ac840cddf5d5ca98e4dc99a952131cd405e66dc3adc6ad30c862d39913bc2b440%26resize%3D4%26selected%3D255403888%23foto255403888?sig=d74870b64abbb5332149c02cddcc3ff582b9808c65f888be26d4ab60823f1a75&width=600&auto=webp",
    "link": "https://www.pararius.nl/huis-te-koop/beuningen-gld/a97ad3a6/lavendelstraat",
    "provider": "Pararius",
    "date_scraped": "2026-01-10"
  },
  {
    "title": "Haselackers 51",
    "price": 289000,
    "address": "7824 LL Emmen (Angelslo)",
    "size": 50.0,
    "energy_label": "Onbekend",
    "garden_terrace": "Nee",
    "image_url": "https://casco-media-prod.global.ssl.fastly.net/7e0cee11-4f6f-591f-aa76-a0639ca66a38/8b813e2bebe8fa107a53f3677ccddf76.jpg?width=600&auto=webp",
    "link": "https://www.pararius.nl/appartement-te-koop/emmen/7e0cee11/haselackers",
    "provider": "Pararius",
    "date_scraped": "2026-01-10"
  },
  {
    "title": "Graaf van Bronkhorststr 2",
    "price": 429000,
    "address": "6247 BZ Gronsveld (Gronsveld)",
    "size": 50.0,
    "energy_label": "Onbekend",
    "garden_terrace": "Nee",
    "image_url": "https://casco-media-prod.global.ssl.fastly.net/b1973429-e140-5d9d-80cb-e50de92d515f/f3ab1397cd4de62fb1705b28332b3630.jpg?width=600&auto=webp",
    "link": "https://www.pararius.nl/huis-te-koop/gronsveld/b1973429/graaf-van-bronkhorststr",
    "provider": "Pararius",
    "date_scraped": "2026-01-10"
  },
  {
    "title": "Huijgensstraat",
    "price": 295000,
    "address": "4361 CW Westkapelle (Westkapelle)",
    "size": 50.0,
    "energy_label": "Onbekend",
    "garden_terrace": "Nee",
    "image_url": "https://casco-media-prod.global.ssl.fastly.net/listings/api/media/642826a7-eaeb-51e8-9289-0cc48aeb3594/9b0e8018-eec9-5d4f-8cb9-5d0f755b9c06?original_uri=https%3A%2F%2Fimages.realworks.nl%2Fservlets%2Fimages%2Fmedia.objectmedia%2F258338772.webp%3Fcheck%3Dsha256%253Abde09df68b5350179b9bf57b13a5cadf1e88e6c71f93a3e07049da25dd66e09b%26resize%3D4%26selected%3D258338772%23foto258338772?sig=f1401e3b69f913c36c2c74b942ef1e28bf62069bb579fa5f66369d15fde8e29a&width=600&auto=webp",
    "link": "https://www.pararius.nl/huis-te-koop/westkapelle/642826a7/huijgensstraat",
    "provider": "Pararius",
    "date_scraped": "2026-01-10"
  },
  {
    "title": "Breedeweer 22",
    "price": 450000,
    "address": "3343 CE Hendrik-Ido-Ambacht (Krommeweg-Zuid)",
    "size": 50.0,
    "energy_label": "Onbekend",
    "garden_terrace": "Nee",
    "image_url": "https://casco-media-prod.global.ssl.fastly.net/d9095177-b31c-5626-9194-f8bb678e5d57/2457f281948995dbffa92ac444404e3a.jpg?width=600&auto=webp",
    "link": "https://www.pararius.nl/huis-te-koop/hendrik-ido-ambacht/d9095177/breedeweer",
    "provider": "Pararius",
    "date_scraped": "2026-01-10"
  },
  {
    "title": "Harriët Freezerlaan 28",
    "price": 415000,
    "address": "6662 LN Elst (De Brieneshof-De Pas)",
    "size": 50.0,
    "energy_label": "Onbekend",
    "garden_terrace": "Nee",
    "image_url": "https://casco-media-prod.global.ssl.fastly.net/2d2c5830-9a5f-5821-9992-e204e49754b3/b870cfabfb8231903e9d0ca4dcf59b88.jpg?width=600&auto=webp",
    "link": "https://www.pararius.nl/huis-te-koop/elst/2d2c5830/harriet-freezerlaan",
    "provider": "Pararius",
    "date_scraped": "2026-01-10"
  },
  {
    "title": "Jacob van Heemskercklaan 253",
    "price": 325000,
    "address": "3144 DK Maassluis (Het Balkon)",
    "size": 50.0,
    "energy_label": "Onbekend",
    "garden_terrace": "Nee",
    "image_url": "https://casco-media-prod.global.ssl.fastly.net/91fc91db-8206-57f7-a979-83a727f778bb/3d6b6d23115222264c30ec4592b5f213.jpg?width=600&auto=webp",
    "link": "https://www.pararius.nl/appartement-te-koop/maassluis/91fc91db/jacob-van-heemskercklaan",
    "provider": "Pararius",
    "date_scraped": "2026-01-10"
  },
  {
    "title": "Ridder van Dorpstraat",
    "price": 375000,
    "address": "3264 VC Nieuw-Beijerland (Nieuw-Beijerland Woonkern)",
    "size": 50.0,
    "energy_label": "Onbekend",
    "garden_terrace": "Nee",
    "image_url": "https://casco-media-prod.global.ssl.fastly.net/listings/api/media/ef291c35-1387-562c-9c2c-22d238f2c78e/9972c9b5-db58-5aae-9c52-af70e2e3b2c6?original_uri=https%3A%2F%2Fcloud01.topsite.nl%2Fhuysvisie.nl%2Fproperty%2F661%2F258712092-26438_945x625_fit.jpg.webp?sig=3045537505d1326a292063a1fdb51100b53627c86dfe7610c3d4d65428c4e393&width=600&auto=webp",
    "link": "https://www.pararius.nl/huis-te-koop/nieuw-beijerland/ef291c35/ridder-van-dorpstraat",
    "provider": "Pararius",
    "date_scraped": "2026-01-10"
  },
  {
    "title": "Wijnkoopsbaai",
    "price": 445000,
    "address": "2904 BN Capelle aan den IJssel (Baaienbuurt)",
    "size": 50.0,
    "energy_label": "Onbekend",
    "garden_terrace": "Nee",
    "image_url": "https://casco-media-prod.global.ssl.fastly.net/listings/api/media/1da081db-4ddf-5a61-b724-6f6945b5fe02/ef4ea111-2c9a-5709-88ee-af36893ff642?original_uri=https%3A%2F%2Fimages.realworks.nl%2Fservlets%2Fimages%2Fmedia.objectmedia%2F258945590.webp%3Fcheck%3Dsha256%253A700ffca2b5acc4f411859388dcceeefb99572ba8bfbbf3ca471b9a12a005a33b%26resize%3D4%26selected%3D258945590%23foto258945590?sig=c633555450839cb9f7b6a09e3564f1ae5a6857c784a9b94d617f1b905ce7d78b&width=600&auto=webp",
    "link": "https://www.pararius.nl/huis-te-koop/capelle-aan-den-ijssel/1da081db/wijnkoopsbaai",
    "provider": "Pararius",
    "date_scraped": "2026-01-10"
  },
  {
    "title": "Gentiaanvaart",
    "price": 425000,
    "address": "2724 TL Zoetermeer (Seghwaert-Zuid-West)",
    "size": 50.0,
    "energy_label": "Onbekend",
    "garden_terrace": "Nee",
    "image_url": "https://casco-media-prod.global.ssl.fastly.net/listings/api/media/144c5d18-a507-5044-b1fd-b42cd4b3a255/709362ac-f151-5a16-9188-ed63747b4a9a?original_uri=https%3A%2F%2Fimages.realworks.nl%2Fservlets%2Fimages%2Fmedia.objectmedia%2F257620784.webp%3Fcheck%3Dsha256%253A56bf22260f46b6bf09e648e97c9fc47f7c5e06508ed999fae19ba07c0dbd3169%26resize%3D4%26selected%3D257620784%23foto257620784?sig=cfe13024142184425301a32ec17501549aa0b71fe0d281b7318448356a96b3d8&width=600&auto=webp",
    "link": "https://www.pararius.nl/huis-te-koop/zoetermeer/144c5d18/gentiaanvaart",
    "provider": "Pararius",
    "date_scraped": "2026-01-10"
  },
  {
    "title": "Dongelaan 29",
    "price": 349500,
    "address": "5463 JP Veghel (Leest)",
    "size": 50.0,
    "energy_label": "Onbekend",
    "garden_terrace": "Nee",
    "image_url": "https://casco-media-prod.global.ssl.fastly.net/dffd766e-ffca-5a55-be9b-ffdb3a82cd0e/c56355fce5bea42f487c78b5ebba173f.jpg?width=600&auto=webp",
    "link": "https://www.pararius.nl/huis-te-koop/veghel/dffd766e/dongelaan",
    "provider": "Pararius",
    "date_scraped": "2026-01-10"
  },
  {
    "title": "Jan Maenenstraat",
    "price": 368000,
    "address": "6363 AE Wijnandsrade (Wijnandsrade)",
    "size": 50.0,
    "energy_label": "Onbekend",
    "garden_terrace": "Nee",
    "image_url": "https://casco-media-prod.global.ssl.fastly.net/listings/api/media/cf247730-69a4-5576-ac01-6ca381d0c62c/e55b43c5-cb75-5e7e-967a-b5f921524db4?original_uri=https%3A%2F%2Fimages.realworks.nl%2Fservlets%2Fimages%2Fmedia.objectmedia%2F259133194.webp%3Fcheck%3Dsha256%253A4cd3b47d160d59b7d80cc59542451cccd1fa396c039fde1fc04498817f5ac193%26resize%3D4%26selected%3D259133194%23foto259133194?sig=71fe7d89185d6289a1ab0da482c00729ec2f5b7ac30f3f6f3f6433d08bc6beca&width=600&auto=webp",
    "link": "https://www.pararius.nl/huis-te-koop/wijnandsrade/cf247730/jan-maenenstraat",
    "provider": "Pararius",
    "date_scraped": "2026-01-10"
  },
  {
    "title": "Hazelaar 11",
    "price": 289000,
    "address": "6444 DM Brunssum (De Hemelder)",
    "size": 50.0,
    "energy_label": "Onbekend",
    "garden_terrace": "Nee",
    "image_url": "https://casco-media-prod.global.ssl.fastly.net/4b7b518e-143b-5e27-b164-8f277d2adf31/6b24bae94d2c7255d6b859f264843092.jpg?width=600&auto=webp",
    "link": "https://www.pararius.nl/huis-te-koop/brunssum/4b7b518e/hazelaar",
    "provider": "Pararius",
    "date_scraped": "2026-01-10"
  },
  {
    "title": "Klinkerstraat 8 A",
    "price": 299000,
    "address": "4567 CE Clinge (Goukensberg)",
    "size": 50.0,
    "energy_label": "Onbekend",
    "garden_terrace": "Nee",
    "image_url": "https://casco-media-prod.global.ssl.fastly.net/3ea8b156-1dc5-57e0-8028-9b6e44793ae0/6dbc357e29592cd7a3b0229cad2272d3.jpg?width=600&auto=webp",
    "link": "https://www.pararius.nl/huis-te-koop/clinge/3ea8b156/klinkerstraat",
    "provider": "Pararius",
    "date_scraped": "2026-01-10"
  },
  {
    "title": "Tolhuis",
    "price": 450000,
    "address": "6537 MP Nijmegen (Tolhuis)",
    "size": 50.0,
    "energy_label": "Onbekend",
    "garden_terrace": "Nee",
    "image_url": "https://casco-media-prod.global.ssl.fastly.net/listings/api/media/8ba5b42d-1f8b-5a45-820b-9cbbd1dadefd/6d7cd375-f5f9-54a8-9652-6fff82dc112e?original_uri=https%3A%2F%2Fwww.hansjanssen.nl%2Fapp%2Fuploads%2Fsure%2Fmedia%2FNN28978%2FNN28978-186379-Tolhuis-2713-Nijmegen-254822268.jpg?sig=3dac4c8ad4467910f15be00fceb0080d3d02ebf05edf48787d3f383a3b03bb21&width=600&auto=webp",
    "link": "https://www.pararius.nl/huis-te-koop/nijmegen/8ba5b42d/tolhuis",
    "provider": "Pararius",
    "date_scraped": "2026-01-10"
  },
  {
    "title": "Hulckesteijn",
    "price": 145000,
    "address": "3861 MZ Nijkerk (Arkemheen)",
    "size": 50.0,
    "energy_label": "Onbekend",
    "garden_terrace": "Nee",
    "image_url": "https://casco-media-prod.global.ssl.fastly.net/listings/api/media/5ea7cc81-ec5e-5b45-b98b-29c85ba6bb63/b42a944f-e4a8-5753-acbb-a0f658f14af8?original_uri=https%3A%2F%2Fimages.realworks.nl%2Fservlets%2Fimages%2Fmedia.objectmedia%2F145254123.webp%3Fcheck%3Dsha256%253Af2051b94c9085db5e82338424be41a884ed7bc0c01eab10c052d505e09e2615e%26resize%3D4%26selected%3D145254123%23foto145254123?sig=a9e568eb8221e10353f0d849ff9bf47762d665cfbef1362873b562dbb934f468&width=600&auto=webp",
    "link": "https://www.pararius.nl/huis-te-koop/nijkerk/5ea7cc81/hulckesteijn",
    "provider": "Pararius",
    "date_scraped": "2026-01-10"
  },
  {
    "title": "Hulckesteijn",
    "price": 359000,
    "address": "3861 MZ Nijkerk (Arkemheen)",
    "size": 50.0,
    "energy_label": "Onbekend",
    "garden_terrace": "Nee",
    "image_url": "https://casco-media-prod.global.ssl.fastly.net/listings/api/media/49518f5d-ae7a-52d5-a817-516e106bc617/6770d1a2-49c8-57f8-a72d-22f6e3880309?original_uri=https%3A%2F%2Fimages.realworks.nl%2Fservlets%2Fimages%2Fmedia.objectmedia%2F188671257.webp%3Fcheck%3Dsha256%253Aa6c7ad327aad0e79c29d843949d80aceb2a3fb991fe0938b6b4901ce3f6d267b%26resize%3D4%26selected%3D188671257%23foto188671257?sig=373a772661e726589dce477187ac9b665576c8c571e3e22090d6569b2cd70726&width=600&auto=webp",
    "link": "https://www.pararius.nl/huis-te-koop/nijkerk/49518f5d/hulckesteijn",
    "provider": "Pararius",
    "date_scraped": "2026-01-10"
  },
  {
    "title": "Hulckesteijn",
    "price": 279000,
    "address": "3861 MZ Nijkerk (Arkemheen)",
    "size": 50.0,
    "energy_label": "Onbekend",
    "garden_terrace": "Nee",
    "image_url": "https://casco-media-prod.global.ssl.fastly.net/listings/api/media/b5137879-5e87-5a7f-86a9-1833ace82e91/ac26137c-55c0-5a4a-9ce3-1713a5ce0964?original_uri=https%3A%2F%2Fimages.realworks.nl%2Fservlets%2Fimages%2Fmedia.objectmedia%2F137706859.webp%3Fcheck%3Dsha256%253A7f2235d68610227c26a7add7d244d59a605330229b5f74f4ab176d8a512d8d43%26resize%3D4%26selected%3D137706859%23foto137706859?sig=f718a23eaf4ffc6a6671a69b9187aff200fc3d40df386d6af57e040b6fcdbb3a&width=600&auto=webp",
    "link": "https://www.pararius.nl/huis-te-koop/nijkerk/b5137879/hulckesteijn",
    "provider": "Pararius",
    "date_scraped": "2026-01-10"
  },
  {
    "title": "Feiko Clockstraat 45",
    "price": 449000,
    "address": "9665 BC Oude Pekela (Oude Pekela)",
    "size": 50.0,
    "energy_label": "Onbekend",
    "garden_terrace": "Nee",
    "image_url": "https://casco-media-prod.global.ssl.fastly.net/2ef16a80-62ca-5572-853e-34347ca6e5d3/f77107e5e500488a913528afd1a7007c.jpg?width=600&auto=webp",
    "link": "https://www.pararius.nl/huis-te-koop/oude-pekela/2ef16a80/feiko-clockstraat",
    "provider": "Pararius",
    "date_scraped": "2026-01-10"
  },
  {
    "title": "Krengelhoek",
    "price": 395000,
    "address": "5421 NW Gemert (Gemert-Noord)",
    "size": 50.0,
    "energy_label": "Onbekend",
    "garden_terrace": "Nee",
    "image_url": "https://casco-media-prod.global.ssl.fastly.net/listings/api/media/d836e24b-91cf-5019-8259-cd59f552ce40/9382fea0-038d-5911-825a-9396c6f12d88?original_uri=https%3A%2F%2Fimages.realworks.nl%2Fservlets%2Fimages%2Fmedia.objectmedia%2F259349134.webp%3Fcheck%3Dsha256%253Ae8a224c851a2098b3f23a5ffe906ce63e46190e1864a81409a41c400cd828860%26resize%3D4%26selected%3D259349134%23foto259349134?sig=2805461738e45dd56df76faaa993902c987c97c10eaec207af6eabe09ccb6b4b&width=600&auto=webp",
    "link": "https://www.pararius.nl/huis-te-koop/gemert/d836e24b/krengelhoek",
    "provider": "Pararius",
    "date_scraped": "2026-01-10"
  },
  {
    "title": "Niellerveld",
    "price": 425000,
    "address": "6042 TB Roermond (Tegelarijeveld-Broekhin)",
    "size": 50.0,
    "energy_label": "Onbekend",
    "garden_terrace": "Nee",
    "image_url": "https://casco-media-prod.global.ssl.fastly.net/listings/api/media/d3930fda-1738-5178-8f52-629fcd918407/ba807a01-8423-509d-9329-85021446c4d0?original_uri=https%3A%2F%2Fwww.jackfrenken.nl%2Fog_media%2Fwonen_21047_9074146%2F9074146_257023358_medium.jpg?sig=42c5bd4786d6a78c3039e4e994d239b74de1e12e94ad9d99d9ad66d7d74c486b&width=600&auto=webp",
    "link": "https://www.pararius.nl/huis-te-koop/roermond/d3930fda/niellerveld",
    "provider": "Pararius",
    "date_scraped": "2026-01-10"
  },
  {
    "title": "Albert Schweitzerstraat 13",
    "price": 340000,
    "address": "5961 HB Horst (Nieuwstraat)",
    "size": 50.0,
    "energy_label": "Onbekend",
    "garden_terrace": "Nee",
    "image_url": "https://casco-media-prod.global.ssl.fastly.net/379dc26b-175b-5aea-8b4c-e5bb5fa4a3c4/5e4d715b42fa7679aed4848c4f539170.jpg?width=600&auto=webp",
    "link": "https://www.pararius.nl/huis-te-koop/horst/379dc26b/albert-schweitzerstraat",
    "provider": "Pararius",
    "date_scraped": "2026-01-10"
  },
  {
    "title": "Stadhouderslaan",
    "price": 439000,
    "address": "2411 TZ Bodegraven (Zeeheldenbuurt)",
    "size": 50.0,
    "energy_label": "Onbekend",
    "garden_terrace": "Nee",
    "image_url": "https://casco-media-prod.global.ssl.fastly.net/listings/api/media/27306dc9-7af0-5fd1-9ff9-71ff702c11d3/07834840-9388-5f7f-8cb0-5de520cbdd01?original_uri=https%3A%2F%2Fcloud01.topsite.nl%2Fregiomakelaer.nl%2Fproperty%2F166%2F20076969-9390_945x625_fit.jpg?sig=da2d450ee76e7a14d1c9ca821262e9e779885df660a942bb103f1bc5e36692f8&width=600&auto=webp",
    "link": "https://www.pararius.nl/appartement-te-koop/bodegraven/27306dc9/stadhouderslaan",
    "provider": "Pararius",
    "date_scraped": "2026-01-10"
  },
  {
    "title": "Rosmolen",
    "price": 415000,
    "address": "4761 XC Zevenbergen (Lindonk)",
    "size": 50.0,
    "energy_label": "Onbekend",
    "garden_terrace": "Nee",
    "image_url": "https://casco-media-prod.global.ssl.fastly.net/listings/api/media/1cc92e8d-7a0a-5e9a-b75f-9a2a336e7e42/16a8c186-57ac-5897-9d42-6586e54089a2?original_uri=https%3A%2F%2Fimages.realworks.nl%2Fservlets%2Fimages%2Fmedia.objectmedia%2F259083212.webp%3Fcheck%3Dsha256%253A71df3d7ec90d09c20410990c33f43e04b83ffe13c0ad3ab287d87e2b2f1686fb%26resize%3D4%26selected%3D259083212%23foto259083212?sig=03f1e0be447b45dc0f5049af7178c06c466742522306ceaa1e9bafd6218f6486&width=600&auto=webp",
    "link": "https://www.pararius.nl/huis-te-koop/zevenbergen/1cc92e8d/rosmolen",
    "provider": "Pararius",
    "date_scraped": "2026-01-10"
  },
  {
    "title": "Park Hertenwei 49",
    "price": 120000,
    "address": "5094 DX Lage Mierde (Verspreide huizen Lage Mierde)",
    "size": 50.0,
    "energy_label": "Onbekend",
    "garden_terrace": "Nee",
    "image_url": "https://casco-media-prod.global.ssl.fastly.net/c104ddfd-3f8c-5652-b0f6-bc472bb2d9ee/c5216ac253eb185564f7395d6a0e0b5c.jpg?width=600&auto=webp",
    "link": "https://www.pararius.nl/huis-te-koop/lage-mierde/c104ddfd/park-hertenwei",
    "provider": "Pararius",
    "date_scraped": "2026-01-10"
  },
  {
    "title": "Van Dishoeckstraat",
    "price": 395000,
    "address": "4382 XR Vlissingen (Baskensburg Zuid)",
    "size": 50.0,
    "energy_label": "Onbekend",
    "garden_terrace": "Nee",
    "image_url": "https://casco-media-prod.global.ssl.fastly.net/listings/api/media/ad77db6c-063d-56c3-99a0-56d905758b80/9299880b-5b87-54ac-99f1-f9e73f6e5f8b?original_uri=https%3A%2F%2Fimages.realworks.nl%2Fservlets%2Fimages%2Fmedia.objectmedia%2F259009708.webp%3Fcheck%3Dsha256%253Aa8a90082f326a5cdb51e844c18b71d55180cc646367c22048929101e1a79d19d%26resize%3D4%26selected%3D259009708%23foto259009708?sig=4f019e891c971380b82d2d5e4d01af68d6d547d4aa703b17865f10f237d49f19&width=600&auto=webp",
    "link": "https://www.pararius.nl/huis-te-koop/vlissingen/ad77db6c/van-dishoeckstraat",
    "provider": "Pararius",
    "date_scraped": "2026-01-10"
  },
  {
    "title": "Heivlinder 24",
    "price": 425000,
    "address": "4814 SL Breda (Westerpark)",
    "size": 50.0,
    "energy_label": "Onbekend",
    "garden_terrace": "Nee",
    "image_url": "https://casco-media-prod.global.ssl.fastly.net/9ddf0b4d-1c7c-5094-9a91-d85d3936fdca/63d6f930db8b248c837ccb415ae2f1ba.jpg?width=600&auto=webp",
    "link": "https://www.pararius.nl/huis-te-koop/breda/9ddf0b4d/heivlinder",
    "provider": "Pararius",
    "date_scraped": "2026-01-10"
  },
  {
    "title": "Marijkelaan",
    "price": 265000,
    "address": "3248 AS Melissant (Melissant woonkern)",
    "size": 50.0,
    "energy_label": "Onbekend",
    "garden_terrace": "Nee",
    "image_url": "https://casco-media-prod.global.ssl.fastly.net/listings/api/media/161e3895-566d-5ef2-bd3c-5ca73834984d/a3c137d8-bf77-530a-8b49-e0f00b4b7309?original_uri=https%3A%2F%2Fimages.realworks.nl%2Fservlets%2Fimages%2Fmedia.objectmedia%2F256435256.webp%3Fcheck%3Dsha256%253Aea5b2c2c510333e960d711d1f6eea09395b3dda5cd5144a120800e3e3b30525f%26resize%3D4%26selected%3D256435256%23foto256435256?sig=daf71f3404953f67f413177443eafa22683cc8ba66df57f0c0842011e9b67efb&width=600&auto=webp",
    "link": "https://www.pararius.nl/huis-te-koop/melissant/161e3895/marijkelaan",
    "provider": "Pararius",
    "date_scraped": "2026-01-10"
  },
  {
    "title": "Uilendonk 18",
    "price": 450000,
    "address": "5467 CD Veghel (Busselbunders)",
    "size": 50.0,
    "energy_label": "Onbekend",
    "garden_terrace": "Nee",
    "image_url": "https://casco-media-prod.global.ssl.fastly.net/fdee609c-6f11-5707-91ab-bfeed3978a54/48cb6d8d2f5445e8fa84ddca7d451c13.jpg?width=600&auto=webp",
    "link": "https://www.pararius.nl/huis-te-koop/veghel/fdee609c/uilendonk",
    "provider": "Pararius",
    "date_scraped": "2026-01-10"
  },
  {
    "title": "Poppestraat 10",
    "price": 389000,
    "address": "4711 JP St. Willebrord (Sint Willebrord)",
    "size": 50.0,
    "energy_label": "Onbekend",
    "garden_terrace": "Nee",
    "image_url": "https://casco-media-prod.global.ssl.fastly.net/1cb5d6b1-c38f-5f24-bb70-355ce22ab1bc/d7b8309f81e7703a77eb0657a8c54ddc.jpg?width=600&auto=webp",
    "link": "https://www.pararius.nl/huis-te-koop/st-willebrord/1cb5d6b1/poppestraat",
    "provider": "Pararius",
    "date_scraped": "2026-01-10"
  },
  {
    "title": "Florastraat",
    "price": 375000,
    "address": "1531 TB Wormer (Plaszoom)",
    "size": 50.0,
    "energy_label": "Onbekend",
    "garden_terrace": "Nee",
    "image_url": "https://casco-media-prod.global.ssl.fastly.net/listings/api/media/e5301016-8a30-56b4-a5ca-48bae9560270/84704868-c93e-5de4-82fe-90ced6a2ae1c?original_uri=https%3A%2F%2Fimages.realworks.nl%2Fservlets%2Fimages%2Fmedia.objectmedia%2F258796298.webp%3Fcheck%3Dsha256%253A4cc4f328f87368b95aad478ba6333fcb38ec0163ae7e820686f9eaf1224e6a02%26resize%3D4%26selected%3D258796298%23foto258796298?sig=117f994d536c3fff844a566e36b43b749ee35d12802bc504c872c85fc9a2cb95&width=600&auto=webp",
    "link": "https://www.pararius.nl/huis-te-koop/wormer/e5301016/florastraat",
    "provider": "Pararius",
    "date_scraped": "2026-01-10"
  },
  {
    "title": "Broekwal 89",
    "price": 309000,
    "address": "5701 CS Helmond (Beisterveld)",
    "size": 50.0,
    "energy_label": "Onbekend",
    "garden_terrace": "Nee",
    "image_url": "https://casco-media-prod.global.ssl.fastly.net/d65187b8-2639-5973-93ab-6cafb0385555/30934bca546780eec2c419bb199d2728.jpg?width=600&auto=webp",
    "link": "https://www.pararius.nl/huis-te-koop/helmond/d65187b8/broekwal",
    "provider": "Pararius",
    "date_scraped": "2026-01-10"
  },
  {
    "title": "In het Veld 41",
    "price": 349500,
    "address": "5926 VZ Venlo (Kern Hout-Blerick)",
    "size": 50.0,
    "energy_label": "Onbekend",
    "garden_terrace": "Nee",
    "image_url": "https://casco-media-prod.global.ssl.fastly.net/ff0a94be-0690-5f38-aad3-1a7d214bc6c1/e2eb45d6a8cd6f2d3d681c5d2e8f87d2.jpg?width=600&auto=webp",
    "link": "https://www.pararius.nl/huis-te-koop/venlo/ff0a94be/in-het-veld",
    "provider": "Pararius",
    "date_scraped": "2026-01-10"
  },
  {
    "title": "De Wetterkamp 7",
    "price": 359000,
    "address": "8501 PK Joure (Joure, Westermeer)",
    "size": 50.0,
    "energy_label": "Onbekend",
    "garden_terrace": "Nee",
    "image_url": "https://casco-media-prod.global.ssl.fastly.net/09e5f6d5-56e2-5749-8cd5-19c49489c98d/f5b4fd815c98f30246472dd2de49cbca.jpg?width=600&auto=webp",
    "link": "https://www.pararius.nl/huis-te-koop/joure/09e5f6d5/de-wetterkamp",
    "provider": "Pararius",
    "date_scraped": "2026-01-10"
  },
  {
    "title": "Generaal Linckerslaan 22",
    "price": 425000,
    "address": "5623 JV Eindhoven (Generalenbuurt)",
    "size": 50.0,
    "energy_label": "Onbekend",
    "garden_terrace": "Nee",
    "image_url": "https://casco-media-prod.global.ssl.fastly.net/146be9cb-805e-5831-a389-01317ba1762c/fb642e064dce8645d3be9e4a0f916160.jpg?width=600&auto=webp",
    "link": "https://www.pararius.nl/huis-te-koop/eindhoven/146be9cb/generaal-linckerslaan",
    "provider": "Pararius",
    "date_scraped": "2026-01-10"
  },
  {
    "title": "Reeshofbos 40",
    "price": 435000,
    "address": "6718 GD Ede (De Bossen)",
    "size": 50.0,
    "energy_label": "Onbekend",
    "garden_terrace": "Nee",
    "image_url": "https://casco-media-prod.global.ssl.fastly.net/10c4c1a2-5c98-5565-854b-b2106c8c1e9c/006bb69ecd62a73ae21084ecaa284c51.jpg?width=600&auto=webp",
    "link": "https://www.pararius.nl/huis-te-koop/ede/10c4c1a2/reeshofbos",
    "provider": "Pararius",
    "date_scraped": "2026-01-10"
  },
  {
    "title": "Rosakker",
    "price": 395000,
    "address": "5571 PH Bergeijk (Hagelkruis e.o.)",
    "size": 50.0,
    "energy_label": "Onbekend",
    "garden_terrace": "Nee",
    "image_url": "https://casco-media-prod.global.ssl.fastly.net/listings/api/media/fff5c029-4d51-5e49-9426-08876036cb2e/7f3f3ef4-6d8a-5649-900d-aba4844a4944?original_uri=https%3A%2F%2Fimages.realworks.nl%2Fservlets%2Fimages%2Fmedia.objectmedia%2F259264844.webp%3Fcheck%3Dsha256%253Aa66a1e360e61ba19cf1cfcbcf0fc34550e0bc470e2e5004d10de7f2b12a37067%26resize%3D4%26selected%3D259264844%23foto259264844?sig=5516d814ff0e39a504bbf756de052a5df888a6e8c79d2a52dfcf7f3e42958ce8&width=600&auto=webp",
    "link": "https://www.pararius.nl/huis-te-koop/bergeijk/fff5c029/rosakker",
    "provider": "Pararius",
    "date_scraped": "2026-01-10"
  },
  {
    "title": "Lotharingenweg",
    "price": 375000,
    "address": "1827 BJ Alkmaar (Daalmeer-Zuidwest)",
    "size": 50.0,
    "energy_label": "Onbekend",
    "garden_terrace": "Nee",
    "image_url": "https://casco-media-prod.global.ssl.fastly.net/listings/api/media/843efa4c-ee3f-5467-b442-cc690d6d4266/18102221-636c-5e11-aef6-0c302c2af1d8?original_uri=https%3A%2F%2Fimages.realworks.nl%2Fservlets%2Fimages%2Fmedia.objectmedia%2F259105254.webp%3Fcheck%3Dsha256%253A3d193a3a4c7122c67fc979ff0ef690c1390c2dd3fdcb9f76268585804fe85dbc%26resize%3D4%26selected%3D259105254%23foto259105254?sig=c40d37097242d01e4303517dd050037d9be09b938c30ccbb7a07e0241e81e480&width=600&auto=webp",
    "link": "https://www.pararius.nl/huis-te-koop/alkmaar/843efa4c/lotharingenweg",
    "provider": "Pararius",
    "date_scraped": "2026-01-10"
  },
  {
    "title": "Hulckesteijn",
    "price": 349500,
    "address": "3861 MZ Nijkerk (Arkemheen)",
    "size": 50.0,
    "energy_label": "Onbekend",
    "garden_terrace": "Nee",
    "image_url": "https://casco-media-prod.global.ssl.fastly.net/listings/api/media/56d367f8-4d5a-5fb8-b478-59db98f4c0ce/5f2aeab5-9731-5cc6-b7d4-94225b0b7d26?original_uri=https%3A%2F%2Fimages.realworks.nl%2Fservlets%2Fimages%2Fmedia.objectmedia%2F236897004.webp%3Fcheck%3Dsha256%253A543dd2af8fcadf85cd3add5f8bad74fb0585927b8c646437aba2e1ed2e96126e%26resize%3D4%26selected%3D236897004%23foto236897004?sig=e312be9e7a5a04ab4a47ee104cb18a7613908337256539f29bae6a6c54d790a2&width=600&auto=webp",
    "link": "https://www.pararius.nl/huis-te-koop/nijkerk/56d367f8/hulckesteijn",
    "provider": "Pararius",
    "date_scraped": "2026-01-10"
  },
  {
    "title": "Weidehuislaan 11",
    "price": 289500,
    "address": "7602 BN Almelo (Vriezenveenseweg en omgeving Haghoek West)",
    "size": 50.0,
    "energy_label": "Onbekend",
    "garden_terrace": "Nee",
    "image_url": "https://casco-media-prod.global.ssl.fastly.net/2c7213a1-26a9-5e08-9100-83bad73a952e/177be923e7e81f93fa2e1085bcdd5084.jpg?width=600&auto=webp",
    "link": "https://www.pararius.nl/huis-te-koop/almelo/2c7213a1/weidehuislaan",
    "provider": "Pararius",
    "date_scraped": "2026-01-10"
  },
  {
    "title": "De Stoutheuvel 25",
    "price": 449000,
    "address": "5632 MN Eindhoven (Vaartbroek)",
    "size": 50.0,
    "energy_label": "Onbekend",
    "garden_terrace": "Nee",
    "image_url": "https://casco-media-prod.global.ssl.fastly.net/c2d3448e-418b-5059-91fa-3269ebe4c45a/6d1675870ae24f5ca800c968c58c6c5c.jpg?width=600&auto=webp",
    "link": "https://www.pararius.nl/huis-te-koop/eindhoven/c2d3448e/de-stoutheuvel",
    "provider": "Pararius",
    "date_scraped": "2026-01-10"
  },
  {
    "title": "Valeriaanstraat 42",
    "price": 399750,
    "address": "4537 DC Terneuzen (Oude Vaart)",
    "size": 50.0,
    "energy_label": "Onbekend",
    "garden_terrace": "Nee",
    "image_url": "https://casco-media-prod.global.ssl.fastly.net/1d64e23e-297c-5e86-85b2-8ec573786e23/3d229775ed3721d005dcc081783b0ab3.jpg?width=600&auto=webp",
    "link": "https://www.pararius.nl/huis-te-koop/terneuzen/1d64e23e/valeriaanstraat",
    "provider": "Pararius",
    "date_scraped": "2026-01-10"
  },
  {
    "title": "van Caldenborghstraat 1",
    "price": 349000,
    "address": "6247 CE Gronsveld (Gronsveld)",
    "size": 50.0,
    "energy_label": "Onbekend",
    "garden_terrace": "Nee",
    "image_url": "https://casco-media-prod.global.ssl.fastly.net/8b52595e-640d-58e0-b329-ce7b80d0107b/fc5f1a8277dc5c511102cd011580e3d6.jpg?width=600&auto=webp",
    "link": "https://www.pararius.nl/huis-te-koop/gronsveld/8b52595e/van-caldenborghstraat",
    "provider": "Pararius",
    "date_scraped": "2026-01-10"
  },
  {
    "title": "Karveel 54",
    "price": 435000,
    "address": "3904 SP Veenendaal (Schepenbuurt)",
    "size": 50.0,
    "energy_label": "Onbekend",
    "garden_terrace": "Nee",
    "image_url": "https://casco-media-prod.global.ssl.fastly.net/08418ef6-1a8a-5b25-b461-d6acd97a0277/20fb20c82c4f6167bbbd5c6b62b9a48a.png?width=600&auto=webp",
    "link": "https://www.pararius.nl/huis-te-koop/veenendaal/08418ef6/karveel",
    "provider": "Pararius",
    "date_scraped": "2026-01-10"
  },
  {
    "title": "Steinstraat",
    "price": 400000,
    "address": "4791 JA Klundert (Klundert)",
    "size": 50.0,
    "energy_label": "Onbekend",
    "garden_terrace": "Nee",
    "image_url": "https://casco-media-prod.global.ssl.fastly.net/listings/api/media/36057368-2e76-50b1-8546-a88a188b51c4/4708eb8f-d1e6-5a91-8c36-b9d9576508a9?original_uri=https%3A%2F%2Fimages.realworks.nl%2Fservlets%2Fimages%2Fmedia.objectmedia%2F246114636.webp%3Fcheck%3Dsha256%253Aa397e15cbcd81d171ead5effdb75b3665cd1d726fe2bc760286f20df160afa68%26resize%3D4%26selected%3D246114636%23foto246114636?sig=e93e3631b00771f3ae6876507218fd815fc4890ff1235e08af6b4247deb897e1&width=600&auto=webp",
    "link": "https://www.pararius.nl/huis-te-koop/klundert/36057368/steinstraat",
    "provider": "Pararius",
    "date_scraped": "2026-01-10"
  },
  {
    "title": "Hoekakker 12",
    "price": 425000,
    "address": "5534 BE Netersel (Netersel)",
    "size": 50.0,
    "energy_label": "Onbekend",
    "garden_terrace": "Nee",
    "image_url": "https://casco-media-prod.global.ssl.fastly.net/c6263632-5a61-5f8f-9297-8d53cddd8950/4203459d051aefa98bfd9687af4ebaec.jpg?width=600&auto=webp",
    "link": "https://www.pararius.nl/huis-te-koop/netersel/c6263632/hoekakker",
    "provider": "Pararius",
    "date_scraped": "2026-01-10"
  },
  {
    "title": "Varelseweg 211 44",
    "price": 355000,
    "address": "8077 RB Hulshorst (Verspreide huizen Zuiderzeeland Hulshorst)",
    "size": 50.0,
    "energy_label": "Onbekend",
    "garden_terrace": "Nee",
    "image_url": "https://casco-media-prod.global.ssl.fastly.net/11b756fa-7a09-5d82-bf1c-2bbce0d3cfc1/b7d74bf7fc4268eb341f94adcb7fd674.jpg?width=600&auto=webp",
    "link": "https://www.pararius.nl/huis-te-koop/hulshorst/11b756fa/varelseweg",
    "provider": "Pararius",
    "date_scraped": "2026-01-10"
  },
  {
    "title": "Reggestraat",
    "price": 319000,
    "address": "4535 GH Terneuzen (Zeldenrust)",
    "size": 50.0,
    "energy_label": "Onbekend",
    "garden_terrace": "Nee",
    "image_url": "https://casco-media-prod.global.ssl.fastly.net/listings/api/media/360625af-3f3b-59c2-a6af-6aef714fa5c0/d05b0bd8-eebd-5edc-9ea8-2021c3111ad4?original_uri=https%3A%2F%2Fimages.realworks.nl%2Fservlets%2Fimages%2Fmedia.objectmedia%2F259045968.webp%3Fcheck%3Dsha256%253A9555661a21f6beaee97cac047c1c07bb972bc56ff053154fa6233bcc3de7271b%26resize%3D4%26selected%3D259045968%23foto259045968?sig=b3003db94b459cdfea271a16f4a7bc000b5b5e0d427014f11ba1cc5ef0ba30a6&width=600&auto=webp",
    "link": "https://www.pararius.nl/huis-te-koop/terneuzen/360625af/reggestraat",
    "provider": "Pararius",
    "date_scraped": "2026-01-10"
  },
  {
    "title": "Prinses Irenestraat 24",
    "price": 270000,
    "address": "6566 BP Millingen aan de Rijn (Millingen aan de Rijn-Oost)",
    "size": 50.0,
    "energy_label": "Onbekend",
    "garden_terrace": "Nee",
    "image_url": "https://casco-media-prod.global.ssl.fastly.net/585b4301-28cc-554a-86c9-8d90a423c6e8/38f883f3812be4b36ad7315091252e09.jpg?width=600&auto=webp",
    "link": "https://www.pararius.nl/huis-te-koop/millingen-aan-de-rijn/585b4301/prinses-irenestraat",
    "provider": "Pararius",
    "date_scraped": "2026-01-10"
  },
  {
    "title": "Jan Roepespad",
    "price": 249750,
    "address": "9161 CT Hollum (Verspreide huizen Hollum)",
    "size": 50.0,
    "energy_label": "Onbekend",
    "garden_terrace": "Nee",
    "image_url": "https://casco-media-prod.global.ssl.fastly.net/listings/api/media/237d0e08-d4d2-5f09-9dff-63e7fe6931f5/cac83e36-2441-5c07-9bdf-ec035718da67?original_uri=https%3A%2F%2Fimages.realworks.nl%2Fservlets%2Fimages%2Fmedia.objectmedia%2F232682102.webp%3Fcheck%3Dsha256%253Ac43f1a793fc5946f4364ae51098161fe3d24158e15a525b04f6d53dc5f495f32%26resize%3D4%26selected%3D232682102%23foto232682102?sig=2534b968aae67c1ec076c2c2e335035e76316ea7fb8d927266e0a3b9b28df2ca&width=600&auto=webp",
    "link": "https://www.pararius.nl/huis-te-koop/hollum/237d0e08/jan-roepespad",
    "provider": "Pararius",
    "date_scraped": "2026-01-10"
  },
  {
    "title": "De Iep 6",
    "price": 389000,
    "address": "6021 NE Budel (Budel)",
    "size": 50.0,
    "energy_label": "Onbekend",
    "garden_terrace": "Nee",
    "image_url": "https://casco-media-prod.global.ssl.fastly.net/71983efb-b372-5b2f-a637-191dcb7630f1/affab197e3461cfafe7d2f5e2038b204.jpg?width=600&auto=webp",
    "link": "https://www.pararius.nl/huis-te-koop/budel/71983efb/de-iep",
    "provider": "Pararius",
    "date_scraped": "2026-01-10"
  },
  {
    "title": "Hulckesteijn",
    "price": 295000,
    "address": "3861 MZ Nijkerk (Arkemheen)",
    "size": 50.0,
    "energy_label": "Onbekend",
    "garden_terrace": "Nee",
    "image_url": "https://casco-media-prod.global.ssl.fastly.net/listings/api/media/f39e460a-6cf8-511b-bf71-5abf85f29e31/d5f23e27-22c1-5020-9333-b094c521746c?original_uri=https%3A%2F%2Fimages.realworks.nl%2Fservlets%2Fimages%2Fmedia.objectmedia%2F152899341.webp%3Fcheck%3Dsha256%253Ab06f54ccb28493cec2a1bbab3a009dedf8f8ddc09800cbfb8503d0ccb8242629%26resize%3D4%26selected%3D152899341%23foto152899341?sig=fe2316a10516fe6da74e3e56c408e8b6b3eeb015259f78d23b17e8286b4fc670&width=600&auto=webp",
    "link": "https://www.pararius.nl/huis-te-koop/nijkerk/f39e460a/hulckesteijn",
    "provider": "Pararius",
    "date_scraped": "2026-01-10"
  },
  {
    "title": "Bramertweg 20",
    "price": 265000,
    "address": "6129 PL Urmond (Urmond ten oosten van Julianakanaal)",
    "size": 50.0,
    "energy_label": "Onbekend",
    "garden_terrace": "Nee",
    "image_url": "https://casco-media-prod.global.ssl.fastly.net/64a22c46-cf20-5f63-800a-d7317eb1f09f/90aae8b4b0d7455f88c33a7b86bf0a0b.jpg?width=600&auto=webp",
    "link": "https://www.pararius.nl/huis-te-koop/urmond/64a22c46/bramertweg",
    "provider": "Pararius",
    "date_scraped": "2026-01-10"
  },
  {
    "title": "Prinsendijk",
    "price": 335000,
    "address": "3079 TE Rotterdam (Groot IJsselmonde)",
    "size": 50.0,
    "energy_label": "Onbekend",
    "garden_terrace": "Nee",
    "image_url": "https://casco-media-prod.global.ssl.fastly.net/listings/api/media/84ac230c-3923-5bf3-87cd-f95e536ccaf1/3fa308f7-16d6-5a45-a2ac-66b2cad91c5f?original_uri=https%3A%2F%2Fcloud01.topsite.nl%2Fhuysvisie.nl%2Fproperty%2F658%2F259137358-26287_945x625_fit.jpg.webp?sig=91e31933a6055077078b46d1b019ba810c33035b42e2faaad1e7504d7bfb30ec&width=600&auto=webp",
    "link": "https://www.pararius.nl/appartement-te-koop/rotterdam/84ac230c/prinsendijk",
    "provider": "Pararius",
    "date_scraped": "2026-01-10"
  },
  {
    "title": "Molenstraat 80 B",
    "price": 345000,
    "address": "4567 BE Clinge (Durpe)",
    "size": 50.0,
    "energy_label": "Onbekend",
    "garden_terrace": "Nee",
    "image_url": "https://casco-media-prod.global.ssl.fastly.net/5d2e3ffc-d796-54b0-b950-fb3403ad5d08/fb869fcb7465f15f03667c3fb9652db8.jpg?width=600&auto=webp",
    "link": "https://www.pararius.nl/huis-te-koop/clinge/5d2e3ffc/molenstraat",
    "provider": "Pararius",
    "date_scraped": "2026-01-10"
  },
  {
    "title": "Binnenpad",
    "price": 215000,
    "address": "8355 BR Giethoorn (Giethoorn-Zuid)",
    "size": 50.0,
    "energy_label": "Onbekend",
    "garden_terrace": "Nee",
    "image_url": "https://casco-media-prod.global.ssl.fastly.net/listings/api/media/7e388f83-004e-5db5-af45-3864c669b48d/0535baa3-9b67-5943-876e-cf4b277f129b?original_uri=https%3A%2F%2Fimages.realworks.nl%2Fservlets%2Fimages%2Fmedia.objectmedia%2F209603109.webp%3Fcheck%3Dsha256%253Ab9d1bb3b5ddb3517ed5eb7a3d4fb2be2b8e940889c176e10cc7b8272e825cb0a%26resize%3D4%26selected%3D209603109%23foto209603109?sig=4459fafff2ce73cfa1dc1b3bbf8101d424326dc7c1d3adc074830897c35d73db&width=600&auto=webp",
    "link": "https://www.pararius.nl/appartement-te-koop/giethoorn/7e388f83/binnenpad",
    "provider": "Pararius",
    "date_scraped": "2026-01-10"
  },
  {
    "title": "Hommelweg",
    "price": 339000,
    "address": "6114 RT Susteren (Recreatiepark Hommelheide)",
    "size": 50.0,
    "energy_label": "Onbekend",
    "garden_terrace": "Nee",
    "image_url": "https://casco-media-prod.global.ssl.fastly.net/listings/api/media/902c6685-ec8b-56a3-86f4-468bdf2523c8/ed07fa89-bfb7-56aa-8e1f-ba4cbd7484ca?original_uri=https%3A%2F%2Fimages.realworks.nl%2Fservlets%2Fimages%2Fmedia.objectmedia%2F228518462.webp%3Fcheck%3Dsha256%253A9a7962e1ed6d8b4ebc99e1ef4857c85330c5ef3bdeff36c7c0e89decadc2c2c8%26resize%3D4%26selected%3D228518462%23foto228518462?sig=c8dcda76d78d1a9e655e7469324c72f0021a2b0e911b4e5e36798f9c66a88176&width=600&auto=webp",
    "link": "https://www.pararius.nl/appartement-te-koop/susteren/902c6685/hommelweg",
    "provider": "Pararius",
    "date_scraped": "2026-01-10"
  },
  {
    "title": "Vouerweg 46",
    "price": 425000,
    "address": "6136 AL Sittard (Overhoven)",
    "size": 50.0,
    "energy_label": "Onbekend",
    "garden_terrace": "Nee",
    "image_url": "https://casco-media-prod.global.ssl.fastly.net/a9f10576-34ee-543d-bead-1e8d4ecdb301/3a8aee8b97df19757a8a53a07b7b9312.jpg?width=600&auto=webp",
    "link": "https://www.pararius.nl/huis-te-koop/sittard/a9f10576/vouerweg",
    "provider": "Pararius",
    "date_scraped": "2026-01-10"
  },
  {
    "title": "Hommelweg",
    "price": 110000,
    "address": "6114 RT Susteren (Recreatiepark Hommelheide)",
    "size": 50.0,
    "energy_label": "Onbekend",
    "garden_terrace": "Nee",
    "image_url": "https://casco-media-prod.global.ssl.fastly.net/listings/api/media/dc0f2010-b55d-5eca-8b76-2b7b983d186e/138c84e2-97c3-577e-9864-3433c55eb6f3?original_uri=https%3A%2F%2Fimages.realworks.nl%2Fservlets%2Fimages%2Fmedia.objectmedia%2F232591848.webp%3Fcheck%3Dsha256%253A89496e71fddb9ad8f0c607558179fd1aff4efde9b57b196916670dbedadec3d2%26resize%3D4%26selected%3D232591848%23foto232591848?sig=e6721af03cfb818320d5e39fca4a43008ce6694d0a2bc5d164be3a9c0091f528&width=600&auto=webp",
    "link": "https://www.pararius.nl/huis-te-koop/susteren/dc0f2010/hommelweg",
    "provider": "Pararius",
    "date_scraped": "2026-01-10"
  },
  {
    "title": "Langeweg",
    "price": 325000,
    "address": "4511 RN Breskens (Verspreide huizen Breskens)",
    "size": 50.0,
    "energy_label": "Onbekend",
    "garden_terrace": "Nee",
    "image_url": "https://casco-media-prod.global.ssl.fastly.net/listings/api/media/0b286e9f-db05-5f50-96ca-53167d52f3f8/829e78d4-c408-57c5-840b-754fb60ff0fd?original_uri=https%3A%2F%2Fimages.realworks.nl%2Fservlets%2Fimages%2Fmedia.objectmedia%2F164579441.webp%3Fcheck%3Dsha256%253Ad86d81e6d9c72845d6a0f695e761cfe824d37c9a3f147884c53da6b42d6d5b45%26resize%3D4%26selected%3D164579441%23foto164579441?sig=6f0d4e49524849d3a4c849cb95d05274d35be40b7b901b635ab2f2ed1f1cec1c&width=600&auto=webp",
    "link": "https://www.pararius.nl/huis-te-koop/breskens/0b286e9f/langeweg",
    "provider": "Pararius",
    "date_scraped": "2026-01-10"
  },
  {
    "title": "Korhoen",
    "price": 179500,
    "address": "7693 VA Sibculo (Verspreide huizen Sibculo)",
    "size": 50.0,
    "energy_label": "Onbekend",
    "garden_terrace": "Nee",
    "image_url": "https://casco-media-prod.global.ssl.fastly.net/listings/api/media/3489ef1c-f988-5831-b6ee-d855a551991a/5a937c3c-bb0c-5cc3-89b9-a9d55686b64d?original_uri=https%3A%2F%2Fimages.realworks.nl%2Fservlets%2Fimages%2Fmedia.objectmedia%2F248410146.webp%3Fcheck%3Dsha256%253A5c3478074f4dabcc19955d8d7352a9feaa4d0e2730f88be5148fe81523500132%26resize%3D4%26selected%3D248410146%23foto248410146?sig=871c5b2d9d7706e488d5ba457a139638d2bbf9179890baade54eb378485213be&width=600&auto=webp",
    "link": "https://www.pararius.nl/huis-te-koop/sibculo-hardenberg/3489ef1c/korhoen",
    "provider": "Pararius",
    "date_scraped": "2026-01-10"
  },
  {
    "title": "Tesselschadelaan 7",
    "price": 435000,
    "address": "5702 DD Helmond (Binderen)",
    "size": 50.0,
    "energy_label": "Onbekend",
    "garden_terrace": "Nee",
    "image_url": "https://casco-media-prod.global.ssl.fastly.net/3220187e-7a3a-5d23-a7ec-9d4abe256e68/e1522f7337ae71c61a60b0acfb1ad49c.jpg?width=600&auto=webp",
    "link": "https://www.pararius.nl/huis-te-koop/helmond/3220187e/tesselschadelaan",
    "provider": "Pararius",
    "date_scraped": "2026-01-10"
  },
  {
    "title": "de Plevier 36",
    "price": 439000,
    "address": "7591 JH Denekamp (Janskamp)",
    "size": 50.0,
    "energy_label": "Onbekend",
    "garden_terrace": "Nee",
    "image_url": "https://casco-media-prod.global.ssl.fastly.net/05234555-115f-599f-868f-28f7cdd21d79/9101b714a57e13055e5d4e2c3d19a820.jpg?width=600&auto=webp",
    "link": "https://www.pararius.nl/huis-te-koop/denekamp/05234555/de-plevier",
    "provider": "Pararius",
    "date_scraped": "2026-01-10"
  },
  {
    "title": "De Gavere",
    "price": 325000,
    "address": "8437 PM Zorgvlied (Verspreide huizen Zorgvlied)",
    "size": 50.0,
    "energy_label": "Onbekend",
    "garden_terrace": "Nee",
    "image_url": "https://casco-media-prod.global.ssl.fastly.net/listings/api/media/a9c0771a-3206-58a7-b431-eea03d7e592d/9fce6161-b9cf-5c33-a930-c54ae39ef8fb?original_uri=https%3A%2F%2Fimages.realworks.nl%2Fservlets%2Fimages%2Fmedia.objectmedia%2F230818036.webp%3Fcheck%3Dsha256%253Ae5aed918a6a62e83a6ccb9d7f946bb0264ac4082d9c3b79d39f0fbf1faf6873d%26resize%3D4%26selected%3D230818036%23foto230818036?sig=20b106d85d92f2a3787f8566998d3267c67b07d336f9a50b798275a71ad8bbbf&width=600&auto=webp",
    "link": "https://www.pararius.nl/huis-te-koop/zorgvlied/a9c0771a/de-gavere",
    "provider": "Pararius",
    "date_scraped": "2026-01-10"
  },
  {
    "title": "Dwingelerweg",
    "price": 398000,
    "address": "7964 KJ Ansen (Verspreide huizen Ansen)",
    "size": 50.0,
    "energy_label": "Onbekend",
    "garden_terrace": "Nee",
    "image_url": "https://casco-media-prod.global.ssl.fastly.net/listings/api/media/5a89f03d-c4cf-5b56-99be-443ee1df7233/e8ede0b2-cdd9-55bb-9d3b-6069c19c983a?original_uri=https%3A%2F%2Fimages.realworks.nl%2Fservlets%2Fimages%2Fmedia.objectmedia%2F150856339.webp%3Fcheck%3Dsha256%253A0cf289181061813afa05f3b437f6fa4c1cc0d4d41be77b11c6196ff84f27f946%26resize%3D4%26selected%3D150856339%23foto150856339?sig=7360463f8b44ce76924c2c411a0b6c24132558cc152751f60b29d15b34566fcd&width=600&auto=webp",
    "link": "https://www.pararius.nl/huis-te-koop/ansen-de-wolden/5a89f03d/dwingelerweg",
    "provider": "Pararius",
    "date_scraped": "2026-01-10"
  },
  {
    "title": "Beek en Brink",
    "price": 319500,
    "address": "8437 PJ Zorgvlied (Verspreide huizen Zorgvlied)",
    "size": 50.0,
    "energy_label": "Onbekend",
    "garden_terrace": "Nee",
    "image_url": "https://casco-media-prod.global.ssl.fastly.net/listings/api/media/9afeb5c0-9f66-5d2e-8b9c-00eccf44405e/87b15fb2-73e7-5a4a-92ab-7b5204216847?original_uri=https%3A%2F%2Fimages.realworks.nl%2Fservlets%2Fimages%2Fmedia.objectmedia%2F249875968.webp%3Fcheck%3Dsha256%253Abacf69dd538041ca673388e3f10e1ed29b200a72855807ef496c49d3131a834f%26resize%3D4%26selected%3D249875968%23foto249875968?sig=a0f8ee47b7d210a39531b6d43d2816e5a27f09742853a863b7c4dafe47937253&width=600&auto=webp",
    "link": "https://www.pararius.nl/huis-te-koop/zorgvlied/9afeb5c0/beek-en-brink",
    "provider": "Pararius",
    "date_scraped": "2026-01-10"
  },
  {
    "title": "Bosstraat 13",
    "price": 269000,
    "address": "6114 AV Susteren (Heide)",
    "size": 50.0,
    "energy_label": "Onbekend",
    "garden_terrace": "Nee",
    "image_url": "https://casco-media-prod.global.ssl.fastly.net/5faa0da4-2aaa-585a-912d-e0d206e7571c/4218c9ec17d877f26e956d81449bf054.jpg?width=600&auto=webp",
    "link": "https://www.pararius.nl/huis-te-koop/susteren/5faa0da4/bosstraat",
    "provider": "Pararius",
    "date_scraped": "2026-01-10"
  },
  {
    "title": "Schumerstraat",
    "price": 295000,
    "address": "8384 EN Wilhelminaoord (Wilhelminaoord)",
    "size": 50.0,
    "energy_label": "Onbekend",
    "garden_terrace": "Nee",
    "image_url": "https://casco-media-prod.global.ssl.fastly.net/listings/api/media/442c4a0a-8743-5296-b1d1-93db1b9c4c49/cb70cfce-aa52-5e2a-be03-3b3e469b2a12?original_uri=https%3A%2F%2Fimages.realworks.nl%2Fservlets%2Fimages%2Fmedia.objectmedia%2F244970644.webp%3Fcheck%3Dsha256%253Afbf3084669ea3f4317d9f6da4034f54c515bdc8b7c25aa18a9e8107af3c57903%26resize%3D4%26selected%3D244970644%23foto244970644?sig=21566a3f2dcc12cd2487dd1acbb693e7472211623f26f6b24ce949c75408375d&width=600&auto=webp",
    "link": "https://www.pararius.nl/huis-te-koop/wilhelminaoord/442c4a0a/schumerstraat",
    "provider": "Pararius",
    "date_scraped": "2026-01-10"
  },
  {
    "title": "Kibbelstuk",
    "price": 440000,
    "address": "7991 EE Dwingeloo (Dwingeloo)",
    "size": 50.0,
    "energy_label": "Onbekend",
    "garden_terrace": "Nee",
    "image_url": "https://casco-media-prod.global.ssl.fastly.net/listings/api/media/d30061d6-904f-537d-9413-f59a5f69f75e/120ef94b-6969-5635-8fdd-95dbf1486b06?original_uri=https%3A%2F%2Fimages.realworks.nl%2Fservlets%2Fimages%2Fmedia.objectmedia%2F248720179.webp%3Fcheck%3Dsha256%253Aa73307f19ea69911bf42edfba4d6a29c429bc2a15cdc470a27044045460de4d5%26resize%3D4%26selected%3D248720179%23foto248720179?sig=1104c076241207aeb613240bab05964bedc9ba95ae3f281673a70d2f991e6612&width=600&auto=webp",
    "link": "https://www.pararius.nl/huis-te-koop/dwingeloo/d30061d6/kibbelstuk",
    "provider": "Pararius",
    "date_scraped": "2026-01-10"
  },
  {
    "title": "'t Hertenspoor",
    "price": 245000,
    "address": "7981 KB Diever (Verspreide huizen Diever)",
    "size": 50.0,
    "energy_label": "Onbekend",
    "garden_terrace": "Nee",
    "image_url": "https://casco-media-prod.global.ssl.fastly.net/listings/api/media/17d0452c-b18c-553a-a547-b3c10b95e6eb/5871a9d0-ce19-570d-89d6-7f4788182c78?original_uri=https%3A%2F%2Fimages.realworks.nl%2Fservlets%2Fimages%2Fmedia.objectmedia%2F226061742.webp%3Fcheck%3Dsha256%253A14c54eba06e1f219abc2394bc5d0ad7b015485a0b3e66e0d24513da5100311d3%26resize%3D4%26selected%3D226061742%23foto226061742?sig=16402503ca4eae3c99d1cd92ae9f33ba068b8833eca7010f60ed6c128e6e763b&width=600&auto=webp",
    "link": "https://www.pararius.nl/huis-te-koop/diever/17d0452c/t-hertenspoor",
    "provider": "Pararius",
    "date_scraped": "2026-01-10"
  },
  {
    "title": "Lootenstraat",
    "price": 349500,
    "address": "9423 RM Hoogersmilde (Hoogersmilde-Centrum)",
    "size": 50.0,
    "energy_label": "Onbekend",
    "garden_terrace": "Nee",
    "image_url": "https://casco-media-prod.global.ssl.fastly.net/listings/api/media/7c5cd900-5977-5dbe-ad33-53953cb4dd70/0cfda6f8-0477-5ff8-ae8a-962866c38873?original_uri=https%3A%2F%2Fimages.realworks.nl%2Fservlets%2Fimages%2Fmedia.objectmedia%2F250534982.webp%3Fcheck%3Dsha256%253A20101fe1d40f991a773755a304a471302d58ad108144d9d7caa3635679233397%26resize%3D4%26selected%3D250534982%23foto250534982?sig=cf2a444dacf62d1024b3d7c480b035b8fb292cc16a4f0fdf159260c4cda4edbb&width=600&auto=webp",
    "link": "https://www.pararius.nl/huis-te-koop/hoogersmilde-midden-drenthe/7c5cd900/lootenstraat",
    "provider": "Pararius",
    "date_scraped": "2026-01-10"
  },
  {
    "title": "Hooybrink",
    "price": 439500,
    "address": "8381 DE Vledder (Vledder)",
    "size": 50.0,
    "energy_label": "Onbekend",
    "garden_terrace": "Nee",
    "image_url": "https://casco-media-prod.global.ssl.fastly.net/listings/api/media/f5e715be-604f-529b-aae5-7f2c2f54ff9f/067fa86b-3845-54ec-9738-bfa17af51be6?original_uri=https%3A%2F%2Fimages.realworks.nl%2Fservlets%2Fimages%2Fmedia.objectmedia%2F246762226.webp%3Fcheck%3Dsha256%253Ab55fc0ded8c9ba7e47800d2ed585b26f74cf0fd85d14a94af78c0fa113bf0c1b%26resize%3D4%26selected%3D246762226%23foto246762226?sig=1258cd97749787d3c3791c20e8c4b11bb59cc260eab95fc4e029dafa8438b11c&width=600&auto=webp",
    "link": "https://www.pararius.nl/huis-te-koop/vledder/f5e715be/hooybrink",
    "provider": "Pararius",
    "date_scraped": "2026-01-10"
  },
  {
    "title": "Broekemastraat",
    "price": 369000,
    "address": "7981 DM Diever (Diever)",
    "size": 50.0,
    "energy_label": "Onbekend",
    "garden_terrace": "Nee",
    "image_url": "https://casco-media-prod.global.ssl.fastly.net/listings/api/media/2ff41a50-213e-5915-af9c-1980122fae8f/1fea9d85-867b-5bed-8312-c1864a28d1ce?original_uri=https%3A%2F%2Fimages.realworks.nl%2Fservlets%2Fimages%2Fmedia.objectmedia%2F249089596.webp%3Fcheck%3Dsha256%253A45455a90aee8bd221f28888ec9ed3731107fb48ad40a481c38c44d4aa82bafe8%26resize%3D4%26selected%3D249089596%23foto249089596?sig=6c44f8b4ddd0c5524379fac844d5a303d5f834b3f14d83ea0bc633be478fc9f6&width=600&auto=webp",
    "link": "https://www.pararius.nl/huis-te-koop/diever/2ff41a50/broekemastraat",
    "provider": "Pararius",
    "date_scraped": "2026-01-10"
  },
  {
    "title": "Hunerwold State",
    "price": 157500,
    "address": "8438 SL Wateren (Verspreide huizen Zorgvlied)",
    "size": 50.0,
    "energy_label": "Onbekend",
    "garden_terrace": "Nee",
    "image_url": "https://casco-media-prod.global.ssl.fastly.net/listings/api/media/f954a8ae-1bb9-5a75-9347-a4fd750e9d7e/d0bdea06-f1c9-57c0-81af-9e4b9a73cb1e?original_uri=https%3A%2F%2Fimages.realworks.nl%2Fservlets%2Fimages%2Fmedia.objectmedia%2F201307471.webp%3Fcheck%3Dsha256%253A9558a4eddd13f62dd72bdc28752110e76c95bd94873d861f0b34547de7a9dd38%26resize%3D4%26selected%3D201307471%23foto201307471?sig=be6c4fdc4da884d9007ae50e0395f082c8ab163bbf574aaf05c75b80ab3c0617&width=600&auto=webp",
    "link": "https://www.pararius.nl/huis-te-koop/wateren/f954a8ae/hunerwold-state",
    "provider": "Pararius",
    "date_scraped": "2026-01-10"
  },
  {
    "title": "'t Hertenspoor",
    "price": 298500,
    "address": "7981 KA Diever (Verspreide huizen Diever)",
    "size": 50.0,
    "energy_label": "Onbekend",
    "garden_terrace": "Nee",
    "image_url": "https://casco-media-prod.global.ssl.fastly.net/listings/api/media/f8e1663b-a3f4-585e-af09-fc33c36b76f2/892c07f9-4282-560a-887e-cdd5baa30ab0?original_uri=https%3A%2F%2Fimages.realworks.nl%2Fservlets%2Fimages%2Fmedia.objectmedia%2F246591840.webp%3Fcheck%3Dsha256%253A79b570ef27cd1ebbd23cd98c4f8bc17f5b3e73bd1f0dcd1e5edf19f00aebf321%26resize%3D4%26selected%3D246591840%23foto246591840?sig=83f38ef17102062c357241e3d062fd7b56d63548513570a5257235ff30894726&width=600&auto=webp",
    "link": "https://www.pararius.nl/huis-te-koop/diever/f8e1663b/t-hertenspoor",
    "provider": "Pararius",
    "date_scraped": "2026-01-10"
  },
  {
    "title": "Koele",
    "price": 385000,
    "address": "8426 NB Appelscha (Appelscha-Buitengebied)",
    "size": 50.0,
    "energy_label": "Onbekend",
    "garden_terrace": "Nee",
    "image_url": "https://casco-media-prod.global.ssl.fastly.net/listings/api/media/121a8a56-4f04-5392-9e27-081ab74996b2/ebc3d4fc-3e50-5efd-ade0-645ede28937e?original_uri=https%3A%2F%2Fimages.realworks.nl%2Fservlets%2Fimages%2Fmedia.objectmedia%2F218750029.webp%3Fcheck%3Dsha256%253Ac041163ed1e7e121c99d809fc4e3c562868fe48e2f37d18aad38043330a4a9f5%26resize%3D4%26selected%3D218750029%23foto218750029?sig=14b58136c80cd7e2e92efdf119b0b8197c13f23d6579e509c4b1b1f8b013d8f1&width=600&auto=webp",
    "link": "https://www.pararius.nl/huis-te-koop/appelscha/121a8a56/koele",
    "provider": "Pararius",
    "date_scraped": "2026-01-10"
  },
  {
    "title": "Hunerwold State",
    "price": 159500,
    "address": "8438 SM Wateren (Verspreide huizen Zorgvlied)",
    "size": 50.0,
    "energy_label": "Onbekend",
    "garden_terrace": "Nee",
    "image_url": "https://casco-media-prod.global.ssl.fastly.net/listings/api/media/8bce0dce-ccfc-5007-824d-feb06706d9da/a454f632-9413-509f-8c65-06e4b5116d3d?original_uri=https%3A%2F%2Fimages.realworks.nl%2Fservlets%2Fimages%2Fmedia.objectmedia%2F228033036.webp%3Fcheck%3Dsha256%253A058e95adc2e4763842546001eb0699b239a7d59b5414602daf86f73971ac896c%26resize%3D4%26selected%3D228033036%23foto228033036?sig=d9ddf7b71ed60e7cc0c0df2b79520549cdc1af94a911f535d58050a4009396ac&width=600&auto=webp",
    "link": "https://www.pararius.nl/huis-te-koop/wateren/8bce0dce/hunerwold-state",
    "provider": "Pararius",
    "date_scraped": "2026-01-10"
  },
  {
    "title": "'t Hertenspoor",
    "price": 298500,
    "address": "7981 KB Diever (Verspreide huizen Diever)",
    "size": 50.0,
    "energy_label": "Onbekend",
    "garden_terrace": "Nee",
    "image_url": "https://casco-media-prod.global.ssl.fastly.net/listings/api/media/ab6c6e79-134a-5bb4-92e6-80cef6b2ec12/dd3202a3-5021-5f49-85e1-3237dc81191d?original_uri=https%3A%2F%2Fimages.realworks.nl%2Fservlets%2Fimages%2Fmedia.objectmedia%2F150100401.webp%3Fcheck%3Dsha256%253Abd39e1247ca70bb07934a354f293120b35fc073a392769c52fe7c090bd8c6155%26resize%3D4%26selected%3D150100401%23foto150100401?sig=3db0e65889bf42523f026037c1b76e7eef5297804f9977df1cb811c56e3969fd&width=600&auto=webp",
    "link": "https://www.pararius.nl/huis-te-koop/diever/ab6c6e79/t-hertenspoor",
    "provider": "Pararius",
    "date_scraped": "2026-01-10"
  },
  {
    "title": "Hunerwold State",
    "price": 165000,
    "address": "8438 SM Wateren (Verspreide huizen Zorgvlied)",
    "size": 50.0,
    "energy_label": "Onbekend",
    "garden_terrace": "Nee",
    "image_url": "https://casco-media-prod.global.ssl.fastly.net/listings/api/media/162abf64-af92-5d78-99e1-de79972c2f21/36043382-ad70-5d25-9497-73a90e929b3e?original_uri=https%3A%2F%2Fimages.realworks.nl%2Fservlets%2Fimages%2Fmedia.objectmedia%2F199716533.webp%3Fcheck%3Dsha256%253Ab4630c0582e0ca8c02f00bfd89153c98a35f92ee93d39dbb1bec2c3eb302b3cb%26resize%3D4%26selected%3D199716533%23foto199716533?sig=804405a2f3771b82576516876293a197fa0655d385a0b4f9cdb28ff916f22068&width=600&auto=webp",
    "link": "https://www.pararius.nl/huis-te-koop/wateren/162abf64/hunerwold-state",
    "provider": "Pararius",
    "date_scraped": "2026-01-10"
  },
  {
    "title": "Hunerwold State",
    "price": 149000,
    "address": "8438 SL Wateren (Verspreide huizen Zorgvlied)",
    "size": 50.0,
    "energy_label": "Onbekend",
    "garden_terrace": "Nee",
    "image_url": "https://casco-media-prod.global.ssl.fastly.net/listings/api/media/ee9789c4-9b6f-5d92-9ad0-420217ee4d5d/ca1ed880-7ae0-5b10-949d-0667bf5b62b7?original_uri=https%3A%2F%2Fimages.realworks.nl%2Fservlets%2Fimages%2Fmedia.objectmedia%2F175192617.webp%3Fcheck%3Dsha256%253A019bd6fad7794b41a8f43a6f7f8d8893cbe05ba476078a3a749f9960a982bf47%26resize%3D4%26selected%3D175192617%23foto175192617?sig=18783c07f92b295abd81f2cdc5dddf5764ed36875581e35e4e7bcba80b5d2a60&width=600&auto=webp",
    "link": "https://www.pararius.nl/huis-te-koop/wateren/ee9789c4/hunerwold-state",
    "provider": "Pararius",
    "date_scraped": "2026-01-10"
  },
  {
    "title": "Zellersacker",
    "price": 369000,
    "address": "6546 HG Nijmegen (t Acker)",
    "size": 50.0,
    "energy_label": "Onbekend",
    "garden_terrace": "Nee",
    "image_url": "https://casco-media-prod.global.ssl.fastly.net/listings/api/media/84fa1105-2a65-5200-95f6-5e9ae036927e/2cb432ed-5788-5b06-933a-b3ee3ef6adbb?original_uri=https%3A%2F%2Fimages.realworks.nl%2Fservlets%2Fimages%2Fmedia.objectmedia%2F258174256.webp%3Fcheck%3Dsha256%253A3e17d89c2c76a9e4791daaec082bb880be0ce427daf7cc1cf83f523a34f03a1e%26resize%3D4%26selected%3D258174256%23foto258174256?sig=824feb8342f67acc7dad84a5b9838eb89de851fead128a7ecf83eb5582829c0f&width=600&auto=webp",
    "link": "https://www.pararius.nl/huis-te-koop/nijmegen/84fa1105/zellersacker",
    "provider": "Pararius",
    "date_scraped": "2026-01-10"
  },
  {
    "title": "Kanaalweg-West 77",
    "price": 275000,
    "address": "7691 BW Bergentheim (Bergentheim Kern)",
    "size": 50.0,
    "energy_label": "Onbekend",
    "garden_terrace": "Nee",
    "image_url": "https://casco-media-prod.global.ssl.fastly.net/08bb9c76-f871-59d3-9026-48b721a0073e/0175feda1aa7a6358691dbab51d4de04.jpg?width=600&auto=webp",
    "link": "https://www.pararius.nl/huis-te-koop/bergentheim/08bb9c76/kanaalweg-west",
    "provider": "Pararius",
    "date_scraped": "2026-01-10"
  },
  {
    "title": "Walstro 18",
    "price": 435000,
    "address": "6136 SE Sittard (Stadbroek)",
    "size": 50.0,
    "energy_label": "Onbekend",
    "garden_terrace": "Nee",
    "image_url": "https://casco-media-prod.global.ssl.fastly.net/5d59196c-3eb0-5912-8cf1-efebb0978404/4314c76a597cfe49ca3b7785d9bf8600.jpg?width=600&auto=webp",
    "link": "https://www.pararius.nl/huis-te-koop/sittard/5d59196c/walstro",
    "provider": "Pararius",
    "date_scraped": "2026-01-10"
  },
  {
    "title": "Duiventoren",
    "price": 375000,
    "address": "4731 MX Oudenbosch (Spui)",
    "size": 50.0,
    "energy_label": "Onbekend",
    "garden_terrace": "Nee",
    "image_url": "https://casco-media-prod.global.ssl.fastly.net/listings/api/media/b6f4509c-2e61-53c7-b8c6-eb3a4967b42d/0d7e5409-a45c-5140-8673-07053c05cf90?original_uri=https%3A%2F%2Fimages.realworks.nl%2Fservlets%2Fimages%2Fmedia.objectmedia%2F258741022.webp%3Fcheck%3Dsha256%253A167c373c854f3ca962f95b72ea0f1889f86db81ac8867529f3023d44896f72d5%26resize%3D4%26selected%3D258741022%23foto258741022?sig=08adb3865040b29e1a48405460530a90d6525c871e48c184e67819dca490fb9d&width=600&auto=webp",
    "link": "https://www.pararius.nl/huis-te-koop/oudenbosch/b6f4509c/duiventoren",
    "provider": "Pararius",
    "date_scraped": "2026-01-10"
  },
  {
    "title": "Moutzhofweg",
    "price": 345000,
    "address": "5926 RB Venlo (Kern Hout-Blerick)",
    "size": 50.0,
    "energy_label": "Onbekend",
    "garden_terrace": "Nee",
    "image_url": "https://casco-media-prod.global.ssl.fastly.net/listings/api/media/eb38ae21-5efc-5a79-bc21-5f96bdd1d106/6576076e-f22c-5f72-b122-4238138128a9?original_uri=https%3A%2F%2Fimages.realworks.nl%2Fservlets%2Fimages%2Fmedia.objectmedia%2F258923924.webp%3Fcheck%3Dsha256%253A5a6051d17e84764c7ad65a41c0b4090ba432595f4515f4ced7dfd344f7c5e575%26resize%3D4%26selected%3D258923924%23foto258923924?sig=16f08c7506a193716234fc343e20894b0118259b1f5699160f3b8451bcc6b428&width=600&auto=webp",
    "link": "https://www.pararius.nl/huis-te-koop/venlo/eb38ae21/moutzhofweg",
    "provider": "Pararius",
    "date_scraped": "2026-01-10"
  },
  {
    "title": "Zeldenrustlaan 3",
    "price": 385000,
    "address": "4535 GX Terneuzen (Zeldenrust)",
    "size": 50.0,
    "energy_label": "Onbekend",
    "garden_terrace": "Nee",
    "image_url": "https://casco-media-prod.global.ssl.fastly.net/95f329d1-dff7-5a17-b038-6ba772ee17b0/79cc29e0738819ba2d576516edb9874d.jpg?width=600&auto=webp",
    "link": "https://www.pararius.nl/huis-te-koop/terneuzen/95f329d1/zeldenrustlaan",
    "provider": "Pararius",
    "date_scraped": "2026-01-10"
  },
  {
    "title": "Jan Vermeerlaan",
    "price": 325000,
    "address": "4703 LE Roosendaal (Scherpdeel)",
    "size": 50.0,
    "energy_label": "Onbekend",
    "garden_terrace": "Nee",
    "image_url": "https://casco-media-prod.global.ssl.fastly.net/listings/api/media/fdfdfd06-8c99-5a57-a2b5-fdcff9e0ce39/3156948e-35ce-58da-a987-9102f57b89c8?original_uri=https%3A%2F%2Fimages.realworks.nl%2Fservlets%2Fimages%2Fmedia.objectmedia%2F258682246.webp%3Fcheck%3Dsha256%253Ab88ae569f0e8d5708ac01c2a1d820c819028394479528ca9bc70124955268d58%26resize%3D4%26selected%3D258682246%23foto258682246?sig=2c181e6c59a3530a61b42ef4ade4c17a179c3c3e43cc9424b87ef77c6199ef66&width=600&auto=webp",
    "link": "https://www.pararius.nl/huis-te-koop/roosendaal/fdfdfd06/jan-vermeerlaan",
    "provider": "Pararius",
    "date_scraped": "2026-01-10"
  },
  {
    "title": "Pierre Zeijenstraat",
    "price": 199000,
    "address": "6464 HJ Kerkrade (Vink)",
    "size": 50.0,
    "energy_label": "Onbekend",
    "garden_terrace": "Nee",
    "image_url": "https://casco-media-prod.global.ssl.fastly.net/listings/api/media/43bcfdcf-f608-5dae-acb7-c02a6e3d1be0/0ed74f5e-39f6-5742-ae3e-20b901f9eeec?original_uri=https%3A%2F%2Fimages.realworks.nl%2Fservlets%2Fimages%2Fmedia.objectmedia%2F258444560.webp%3Fcheck%3Dsha256%253Ab370e8e24fe4a87d9ea83314712ff4b3174fe997ab9ea1172b567e5e3c0300b9%26resize%3D4%26selected%3D258444560%23foto258444560?sig=7df861520d64be1c1c789ce9753d7cd0f2e8b582852103301da190ea49e414a7&width=600&auto=webp",
    "link": "https://www.pararius.nl/huis-te-koop/kerkrade/43bcfdcf/pierre-zeijenstraat",
    "provider": "Pararius",
    "date_scraped": "2026-01-10"
  },
  {
    "title": "Ringovenhof 30",
    "price": 399000,
    "address": "5865 BM Tienray (Tienray)",
    "size": 50.0,
    "energy_label": "Onbekend",
    "garden_terrace": "Nee",
    "image_url": "https://casco-media-prod.global.ssl.fastly.net/4cc7fb3a-a1cb-5db3-944a-fcdf9e80c4af/fd53acfe7510bc98d877401a7801bd26.jpg?width=600&auto=webp",
    "link": "https://www.pararius.nl/huis-te-koop/tienray/4cc7fb3a/ringovenhof",
    "provider": "Pararius",
    "date_scraped": "2026-01-10"
  },
  {
    "title": "Karnstraat",
    "price": 450000,
    "address": "1445 KX Purmerend (Maten- en Zuivelbuurt)",
    "size": 50.0,
    "energy_label": "Onbekend",
    "garden_terrace": "Nee",
    "image_url": "https://casco-media-prod.global.ssl.fastly.net/listings/api/media/d77eb63a-9fc3-5398-aa8f-4c7f3f136efb/bca93969-1a3b-530d-9906-912dacf232ea?original_uri=https%3A%2F%2Fimages.realworks.nl%2Fservlets%2Fimages%2Fmedia.objectmedia%2F258019490.webp%3Fcheck%3Dsha256%253A617c750cb1802a24c7aea93550b26d092df73aad6e16ed8507d7fda97efef4f7%26resize%3D4%26selected%3D258019490%23foto258019490?sig=d6499107760ff5e9dd9c30d9a75b2eddb89ebef2bdc38cfd40e84204f190b1c1&width=600&auto=webp",
    "link": "https://www.pararius.nl/huis-te-koop/purmerend/d77eb63a/karnstraat",
    "provider": "Pararius",
    "date_scraped": "2026-01-10"
  },
  {
    "title": "Evert C. Slimstraat 26",
    "price": 240000,
    "address": "9076 EG St.-Annaparochie (St.-Annaparochie Zuidwest)",
    "size": 50.0,
    "energy_label": "Onbekend",
    "garden_terrace": "Nee",
    "image_url": "https://casco-media-prod.global.ssl.fastly.net/5943f4e3-02ef-51e6-8796-5ca7b1fefac9/1573cc5a0f3d073cb433d9e64ce0acc0.jpg?width=600&auto=webp",
    "link": "https://www.pararius.nl/huis-te-koop/st-annaparochie/5943f4e3/evert-c-slimstraat",
    "provider": "Pararius",
    "date_scraped": "2026-01-10"
  },
  {
    "title": "Vroonweg",
    "price": 385000,
    "address": "4356 ET Oostkapelle (Duno)",
    "size": 50.0,
    "energy_label": "Onbekend",
    "garden_terrace": "Nee",
    "image_url": "https://casco-media-prod.global.ssl.fastly.net/listings/api/media/aa7139da-c512-5d8c-8f16-d5552edd782e/e7c2a9ec-619e-5466-a196-00ee14dd123f?original_uri=https%3A%2F%2Fimages.realworks.nl%2Fservlets%2Fimages%2Fmedia.objectmedia%2F228608986.webp%3Fcheck%3Dsha256%253A148ece9183c9fff2fa61eced0b36980c05e9dfb0852091ac43864728f15e9ba3%26resize%3D4%26selected%3D228608986%23foto228608986?sig=a14ad31a4ea802b9a9fc5bc8b05cca8eca6b8f43380dd8ca803e2652b9dc3e70&width=600&auto=webp",
    "link": "https://www.pararius.nl/huis-te-koop/oostkapelle/aa7139da/vroonweg",
    "provider": "Pararius",
    "date_scraped": "2026-01-10"
  },
  {
    "title": "'t Koejepad",
    "price": 415000,
    "address": "3253 XT Ouddorp (Ouddorp zuid)",
    "size": 50.0,
    "energy_label": "Onbekend",
    "garden_terrace": "Nee",
    "image_url": "https://casco-media-prod.global.ssl.fastly.net/listings/api/media/0d6c8b63-a38c-56e4-b29d-e418fc1b3201/3f6a850b-275e-59e6-b75c-d739b85b7c4c?original_uri=https%3A%2F%2Fimages.realworks.nl%2Fservlets%2Fimages%2Fmedia.objectmedia%2F258336926.webp%3Fcheck%3Dsha256%253Ac727326e95b4f36a52d7fcb716b3e67741ffb3a457b744913ead878ae4f8a8f0%26resize%3D4%26selected%3D258336926%23foto258336926?sig=ed85e8a6519865fa807ca6cb9a9bdbc12a96e3b9fd4cce35c4699b2f764bd80d&width=600&auto=webp",
    "link": "https://www.pararius.nl/huis-te-koop/ouddorp/0d6c8b63/t-koejepad",
    "provider": "Pararius",
    "date_scraped": "2026-01-10"
  },
  {
    "title": "Vroonweg",
    "price": 385000,
    "address": "4356 ET Oostkapelle (Duno)",
    "size": 50.0,
    "energy_label": "Onbekend",
    "garden_terrace": "Nee",
    "image_url": "https://casco-media-prod.global.ssl.fastly.net/listings/api/media/6f93cc3b-5b14-5765-b994-c5c32a6fbe44/cf3ea3d8-0022-5ccb-84a7-47706ef368fa?original_uri=https%3A%2F%2Fimages.realworks.nl%2Fservlets%2Fimages%2Fmedia.objectmedia%2F234195030.webp%3Fcheck%3Dsha256%253A95985a0efff37b2dcfae672162842518e7f455a212563330f5908ba59a427a57%26resize%3D4%26selected%3D234195030%23foto234195030?sig=4fbb0d50395338a3ec4ffd2fcd3dac66a719ea7829d290062cdd60f057e97eb3&width=600&auto=webp",
    "link": "https://www.pararius.nl/huis-te-koop/oostkapelle/6f93cc3b/vroonweg",
    "provider": "Pararius",
    "date_scraped": "2026-01-10"
  },
  {
    "title": "Elisabeth Gruytersstraat 15",
    "price": 450000,
    "address": "6216 EN Maastricht (Brusselsepoort)",
    "size": 50.0,
    "energy_label": "Onbekend",
    "garden_terrace": "Nee",
    "image_url": "https://casco-media-prod.global.ssl.fastly.net/40652c26-c0b9-508f-bb11-06f421bf0fed/936ed9d8aa0bb0454023609f5f44f16d.jpg?width=600&auto=webp",
    "link": "https://www.pararius.nl/huis-te-koop/maastricht/40652c26/elisabeth-gruytersstraat",
    "provider": "Pararius",
    "date_scraped": "2026-01-10"
  },
  {
    "title": "Vroonweg",
    "price": 409000,
    "address": "4356 ET Oostkapelle (Duno)",
    "size": 50.0,
    "energy_label": "Onbekend",
    "garden_terrace": "Nee",
    "image_url": "https://casco-media-prod.global.ssl.fastly.net/listings/api/media/3ccb8cfb-12e2-569f-83cf-67a61ad2f745/c7da26ee-5f70-5955-9ba5-533facc88544?original_uri=https%3A%2F%2Fimages.realworks.nl%2Fservlets%2Fimages%2Fmedia.objectmedia%2F231505614.webp%3Fcheck%3Dsha256%253Aab7c88b6a526c2bf6e19a4aa317424020c514830c680cc628c0e7a30b533e17b%26resize%3D4%26selected%3D231505614%23foto231505614?sig=4f90d40a64658f27ba30c0b3f6480cc6b295335851aaa1f9c169d7a76018b03b&width=600&auto=webp",
    "link": "https://www.pararius.nl/huis-te-koop/oostkapelle/3ccb8cfb/vroonweg",
    "provider": "Pararius",
    "date_scraped": "2026-01-10"
  },
  {
    "title": "Marslaan",
    "price": 385000,
    "address": "3318 JG Dordrecht (Sterrenburg 1-West)",
    "size": 50.0,
    "energy_label": "Onbekend",
    "garden_terrace": "Nee",
    "image_url": "https://casco-media-prod.global.ssl.fastly.net/listings/api/media/cab4453d-2787-5af7-a352-bcf2092a8349/154e48ea-3233-58ae-b3ee-d2933c262b31?original_uri=https%3A%2F%2Fimages.realworks.nl%2Fservlets%2Fimages%2Fmedia.objectmedia%2F258107938.webp%3Fcheck%3Dsha256%253A186412be8a2d4dff5d7f1c21b85da2c423769b0725f3dd756f086be0e10eeefd%26resize%3D4%26selected%3D258107938%23foto258107938?sig=d0a6d4f785d60be181b094c51ba2f80230e8474c685d8a54ae829ebe50cf9b8b&width=600&auto=webp",
    "link": "https://www.pararius.nl/appartement-te-koop/dordrecht/cab4453d/marslaan",
    "provider": "Pararius",
    "date_scraped": "2026-01-10"
  },
  {
    "title": "Voltalaan",
    "price": 250000,
    "address": "6431 CL Hoensbroek (Mariarade-Zuid)",
    "size": 50.0,
    "energy_label": "Onbekend",
    "garden_terrace": "Nee",
    "image_url": "https://casco-media-prod.global.ssl.fastly.net/listings/api/media/a8861ea4-fc00-5a7a-8fa7-cb53cd400654/4d2f67c2-4be2-5a80-9694-48dda5e7972e?original_uri=https%3A%2F%2Fimages.realworks.nl%2Fservlets%2Fimages%2Fmedia.objectmedia%2F257882374.webp%3Fcheck%3Dsha256%253A486215f4c20168dc8e48ba588a341748c91078611bafa0995827c85258a86fa1%26resize%3D4%26selected%3D257882374%23foto257882374?sig=5f24d4234b33f5ed1360c307c21ca4d07abaafaf17cf70412ec4de5eef867383&width=600&auto=webp",
    "link": "https://www.pararius.nl/huis-te-koop/hoensbroek/a8861ea4/voltalaan",
    "provider": "Pararius",
    "date_scraped": "2026-01-10"
  },
  {
    "title": "De Els 8",
    "price": 425000,
    "address": "6021 NG Budel (Budel)",
    "size": 50.0,
    "energy_label": "Onbekend",
    "garden_terrace": "Nee",
    "image_url": "https://casco-media-prod.global.ssl.fastly.net/ca58fccd-0249-56ed-a3a7-da1191ab863e/0f9be030fbba4b06c443ffa8c1bfd30a.jpg?width=600&auto=webp",
    "link": "https://www.pararius.nl/huis-te-koop/budel/ca58fccd/de-els",
    "provider": "Pararius",
    "date_scraped": "2026-01-10"
  },
  {
    "title": "Vroonweg",
    "price": 395000,
    "address": "4356 ET Oostkapelle (Duno)",
    "size": 50.0,
    "energy_label": "Onbekend",
    "garden_terrace": "Nee",
    "image_url": "https://casco-media-prod.global.ssl.fastly.net/listings/api/media/96208174-8922-580f-a895-c6593dd81799/9c25f819-09b6-5e82-ac55-c9fbde24e5ab?original_uri=https%3A%2F%2Fimages.realworks.nl%2Fservlets%2Fimages%2Fmedia.objectmedia%2F200098293.webp%3Fcheck%3Dsha256%253A0c0fd1abd547df84115ff792480805fadeb3e4baf21b24c07e8a38f6c9fe08f5%26resize%3D4%26selected%3D200098293%23foto200098293?sig=1fa5c7e7153d36d08ca57120533675c2d035d9d54e9dddf89e650cd7ef9d315e&width=600&auto=webp",
    "link": "https://www.pararius.nl/huis-te-koop/oostkapelle/96208174/vroonweg",
    "provider": "Pararius",
    "date_scraped": "2026-01-10"
  },
  {
    "title": "Bergstraat",
    "price": 399000,
    "address": "4365 BD Meliskerke (Meliskerke)",
    "size": 50.0,
    "energy_label": "Onbekend",
    "garden_terrace": "Nee",
    "image_url": "https://casco-media-prod.global.ssl.fastly.net/listings/api/media/933ee2d4-601e-5624-9cc5-d07177639586/b1d0971d-0ad6-55c6-88d4-21087ad9b337?original_uri=https%3A%2F%2Fimages.realworks.nl%2Fservlets%2Fimages%2Fmedia.objectmedia%2F258294612.webp%3Fcheck%3Dsha256%253Aa3b9c188a79f4e82f0bd55eba735e7843d5a3dc871e4b831516ad83dac198a88%26resize%3D4%26selected%3D258294612%23foto258294612?sig=9443d03e6c3b186fd58e54c2b62cfb975fd7d6eb3f56d4e60779bebe7be74a79&width=600&auto=webp",
    "link": "https://www.pararius.nl/huis-te-koop/meliskerke/933ee2d4/bergstraat",
    "provider": "Pararius",
    "date_scraped": "2026-01-10"
  },
  {
    "title": "Ridder van Asenrodeweg",
    "price": 349000,
    "address": "6042 LG Roermond (Asenray)",
    "size": 50.0,
    "energy_label": "Onbekend",
    "garden_terrace": "Nee",
    "image_url": "https://casco-media-prod.global.ssl.fastly.net/listings/api/media/c3ead015-23a1-598e-8165-a936fb625324/801952ae-5820-5b91-872f-3036b0ffacfd?original_uri=https%3A%2F%2Fimages.realworks.nl%2Fservlets%2Fimages%2Fmedia.objectmedia%2F245801402.webp%3Fcheck%3Dsha256%253A835e9a839444b9d960fca51a943e6bc815774394ffe542bf653a9b0311202598%26resize%3D4%26selected%3D245801402%23foto245801402?sig=3ea616d40d39435528f2953ad7657dfa8bce035728d01f8901c057b1a76ae18d&width=600&auto=webp",
    "link": "https://www.pararius.nl/huis-te-koop/roermond/c3ead015/ridder-van-asenrodeweg",
    "provider": "Pararius",
    "date_scraped": "2026-01-10"
  },
  {
    "title": "Hogeland 20",
    "price": 395000,
    "address": "2264 JZ Leidschendam ('t Lien noord)",
    "size": 50.0,
    "energy_label": "Onbekend",
    "garden_terrace": "Nee",
    "image_url": "https://casco-media-prod.global.ssl.fastly.net/a67d36e9-66e0-5c6e-8389-0a9170f832bf/7ac1b20a88a168054369ce3e53be71bc.jpg?width=600&auto=webp",
    "link": "https://www.pararius.nl/huis-te-koop/leidschendam/a67d36e9/hogeland",
    "provider": "Pararius",
    "date_scraped": "2026-01-10"
  },
  {
    "title": "Lambertweg 26",
    "price": 319000,
    "address": "5764 PX De Rips (De Rips)",
    "size": 50.0,
    "energy_label": "Onbekend",
    "garden_terrace": "Nee",
    "image_url": "https://casco-media-prod.global.ssl.fastly.net/7991a1ed-53fb-56a5-8fd3-d7cd83240dfe/3a1aa4c2b52ebc09ef1fc9320e0848c9.jpg?width=600&auto=webp",
    "link": "https://www.pararius.nl/huis-te-koop/de-rips/7991a1ed/lambertweg",
    "provider": "Pararius",
    "date_scraped": "2026-01-10"
  },
  {
    "title": "Waterweegbree 12",
    "price": 449000,
    "address": "4823 NC Breda (Kroeten)",
    "size": 50.0,
    "energy_label": "Onbekend",
    "garden_terrace": "Nee",
    "image_url": "https://casco-media-prod.global.ssl.fastly.net/880760a1-4c21-5ac5-aa4f-75a87ba260d5/66a6a0f725804405d61504d3ef083d73.jpg?width=600&auto=webp",
    "link": "https://www.pararius.nl/huis-te-koop/breda/880760a1/waterweegbree",
    "provider": "Pararius",
    "date_scraped": "2026-01-10"
  },
  {
    "title": "Leeuwerikweide 51",
    "price": 400000,
    "address": "3927 SP Renswoude (Verspreide huizen)",
    "size": 50.0,
    "energy_label": "Onbekend",
    "garden_terrace": "Nee",
    "image_url": "https://casco-media-prod.global.ssl.fastly.net/0441cdff-f103-515b-aae2-029958ce7f17/10135c2138288c7fdadc2bd3e4b93f04.jpg?width=600&auto=webp",
    "link": "https://www.pararius.nl/huis-te-koop/renswoude/0441cdff/leeuwerikweide",
    "provider": "Pararius",
    "date_scraped": "2026-01-10"
  },
  {
    "title": "Pienemanstraat 8",
    "price": 395000,
    "address": "6717 WE Ede (De Hoef)",
    "size": 50.0,
    "energy_label": "Onbekend",
    "garden_terrace": "Nee",
    "image_url": "https://casco-media-prod.global.ssl.fastly.net/2eafae09-1b70-591f-ba24-1c777377becd/b3dae7adadaa177fb251354930550f33.jpg?width=600&auto=webp",
    "link": "https://www.pararius.nl/huis-te-koop/ede/2eafae09/pienemanstraat",
    "provider": "Pararius",
    "date_scraped": "2026-01-10"
  },
  {
    "title": "Bolderikplein",
    "price": 395000,
    "address": "6229 TD Maastricht (Heugem)",
    "size": 50.0,
    "energy_label": "Onbekend",
    "garden_terrace": "Nee",
    "image_url": "https://casco-media-prod.global.ssl.fastly.net/listings/api/media/bdfd9abb-a55e-5703-9362-3e359748a5b4/03dd6438-17c2-5664-89a7-fb4b1c642dc6?original_uri=https%3A%2F%2Fimages.realworks.nl%2Fservlets%2Fimages%2Fmedia.objectmedia%2F256083122.webp%3Fcheck%3Dsha256%253A9358569b5d887b6104a7af92e70dc945998b6a57f2d73ad6cdbd3404d7f55ca6%26resize%3D4%26selected%3D256083122%23foto256083122?sig=9c75e4a878f5537e033fac99adc5d3acd137218c681242c8335fac993d86323c&width=600&auto=webp",
    "link": "https://www.pararius.nl/huis-te-koop/maastricht/bdfd9abb/bolderikplein",
    "provider": "Pararius",
    "date_scraped": "2026-01-10"
  },
  {
    "title": "Kornet 21",
    "price": 365000,
    "address": "3068 LN Rotterdam (Zevenkamp)",
    "size": 50.0,
    "energy_label": "Onbekend",
    "garden_terrace": "Nee",
    "image_url": "https://casco-media-prod.global.ssl.fastly.net/2d23c4a2-383a-5f7e-bdf3-523d39e8b090/6f1d8a73894c72d10757485ef9dddb99.jpg?width=600&auto=webp",
    "link": "https://www.pararius.nl/huis-te-koop/rotterdam/2d23c4a2/kornet",
    "provider": "Pararius",
    "date_scraped": "2026-01-10"
  },
  {
    "title": "Pr. Margrietstraat 4",
    "price": 389000,
    "address": "5961 BL Horst (Molenveld)",
    "size": 50.0,
    "energy_label": "Onbekend",
    "garden_terrace": "Nee",
    "image_url": "https://casco-media-prod.global.ssl.fastly.net/7b06c80d-2db7-518b-bebd-2d06c474eccf/c6eab4d24f6407077a94ba5aa23c5fab.jpg?width=600&auto=webp",
    "link": "https://www.pararius.nl/huis-te-koop/horst/7b06c80d/pr-margrietstraat",
    "provider": "Pararius",
    "date_scraped": "2026-01-10"
  },
  {
    "title": "Bosgouw",
    "price": 397500,
    "address": "1352 GG Almere (Bosgouw, Brongouw en Nijvergouw)",
    "size": 50.0,
    "energy_label": "Onbekend",
    "garden_terrace": "Nee",
    "image_url": "https://casco-media-prod.global.ssl.fastly.net/listings/api/media/33b93a89-6ae9-5fa3-b75e-e3c7e62bf10d/69d6c1a2-b4c1-59f3-a964-5f373fdec7f7?original_uri=https%3A%2F%2Fwww.vanderlinden.nl%2Fmedia_bb%2Fthumbs%2F1200x800%2F2571947.jpg?sig=e8308d97ff79a60e624bcad853f3c1ae893807e39e6a27fc0313d6a7d3222687&width=600&auto=webp",
    "link": "https://www.pararius.nl/huis-te-koop/almere/33b93a89/bosgouw",
    "provider": "Pararius",
    "date_scraped": "2026-01-10"
  },
  {
    "title": "Pieter Duvelaer van Campenstraat",
    "price": 315000,
    "address": "4336 AR Middelburg (Magistraatwijk I)",
    "size": 50.0,
    "energy_label": "Onbekend",
    "garden_terrace": "Nee",
    "image_url": "https://casco-media-prod.global.ssl.fastly.net/listings/api/media/06fa88e5-4a53-59e2-91b8-adff6b4ff613/3bf1b920-9067-5fca-8208-d0e4566e6462?original_uri=https%3A%2F%2Fcloud01.topsite.nl%2Fschinkeldeweerd.nl%2Fproperty%2F1962%2F258560878-81988_945x625_fit.jpg.webp?sig=d7e08670d90f0e3ae9b930ac2d4d032797616bdc76cdb91917a267623384c662&width=600&auto=webp",
    "link": "https://www.pararius.nl/huis-te-koop/middelburg/06fa88e5/pieter-duvelaer-van-campenstraat",
    "provider": "Pararius",
    "date_scraped": "2026-01-10"
  },
  {
    "title": "Rozenstraat",
    "price": 195000,
    "address": "4537 SC Terneuzen (Lievenspolder)",
    "size": 50.0,
    "energy_label": "Onbekend",
    "garden_terrace": "Nee",
    "image_url": "https://casco-media-prod.global.ssl.fastly.net/listings/api/media/b132993a-0f07-504a-af50-e75f4a11ec9c/5d8f42cb-afcf-55b5-b624-2638e33c3612?original_uri=https%3A%2F%2Fimages.realworks.nl%2Fservlets%2Fimages%2Fmedia.objectmedia%2F259024818.webp%3Fcheck%3Dsha256%253A33f8e5f542282df24aa5e47c17bb0921deb2100240c29cbb039eeb62cd7d79b5%26resize%3D4%26selected%3D259024818%23foto259024818?sig=4ece1891fe96abc1905eca26a08c1605f7f754e5c4c97328f113f1b8b69a0245&width=600&auto=webp",
    "link": "https://www.pararius.nl/huis-te-koop/terneuzen/b132993a/rozenstraat",
    "provider": "Pararius",
    "date_scraped": "2026-01-10"
  },
  {
    "title": "Bereklauw",
    "price": 340000,
    "address": "8265 GV Kampen (Cellesbroek)",
    "size": 50.0,
    "energy_label": "Onbekend",
    "garden_terrace": "Nee",
    "image_url": "https://casco-media-prod.global.ssl.fastly.net/listings/api/media/1c5f5c16-6605-57ce-b7cb-01718efe9e6a/59544e88-a244-54e8-b2a1-997b9b664d14?original_uri=https%3A%2F%2Fimages.realworks.nl%2Fservlets%2Fimages%2Fmedia.objectmedia%2F257877500.webp%3Fcheck%3Dsha256%253Ab0ad13e9bb466e97c1688766916aeda82d9c54d82c4f3d7c9a196fd29e9aa057%26resize%3D4%26selected%3D257877500%23foto257877500?sig=b0c28a4d5c8bc8355b73d233320d237e65bed20657d15919715eb86636b0c509&width=600&auto=webp",
    "link": "https://www.pararius.nl/huis-te-koop/kampen/1c5f5c16/bereklauw",
    "provider": "Pararius",
    "date_scraped": "2026-01-10"
  },
  {
    "title": "Bereklauw",
    "price": 340000,
    "address": "8265 GV Kampen (Cellesbroek)",
    "size": 50.0,
    "energy_label": "Onbekend",
    "garden_terrace": "Nee",
    "image_url": "https://casco-media-prod.global.ssl.fastly.net/listings/api/media/e3c12dca-77a8-5a10-894c-0b8d99e64d2c/efac72a8-a8d8-5640-99f7-735fb18f80e8?original_uri=https%3A%2F%2Fimages.realworks.nl%2Fservlets%2Fimages%2Fmedia.objectmedia%2F257986614.webp%3Fcheck%3Dsha256%253Ae578d8f4e3dc784e2b3a14799f7cf0358aa4254988d594af4a8f91fa01f2b6e2%26resize%3D4%26selected%3D257986614%23foto257986614?sig=da8bfebe7fa8db163efe496b5a17a7d8cae41b0adf5c66ef4d6f63b7f24a3378&width=600&auto=webp",
    "link": "https://www.pararius.nl/huis-te-koop/kampen/e3c12dca/bereklauw",
    "provider": "Pararius",
    "date_scraped": "2026-01-10"
  },
  {
    "title": "Eburonenhof 27",
    "price": 345000,
    "address": "6004 BT Weert (Leuken)",
    "size": 50.0,
    "energy_label": "Onbekend",
    "garden_terrace": "Nee",
    "image_url": "https://casco-media-prod.global.ssl.fastly.net/89c32e7a-6724-5265-bae4-d7e765961f68/d1d6f3b2fcb13f9776292a076c1d94ae.jpg?width=600&auto=webp",
    "link": "https://www.pararius.nl/huis-te-koop/weert/89c32e7a/eburonenhof",
    "provider": "Pararius",
    "date_scraped": "2026-01-10"
  },
  {
    "title": "Muiderslotstraat 16",
    "price": 399000,
    "address": "5037 HK Tilburg (Kastelenbuurt Noord)",
    "size": 50.0,
    "energy_label": "Onbekend",
    "garden_terrace": "Nee",
    "image_url": "https://casco-media-prod.global.ssl.fastly.net/aa123178-708e-527c-a5e2-b20be112f936/c5ce7cd0c92ef754107a4093e102d625.jpg?width=600&auto=webp",
    "link": "https://www.pararius.nl/huis-te-koop/tilburg/aa123178/muiderslotstraat",
    "provider": "Pararius",
    "date_scraped": "2026-01-10"
  },
  {
    "title": "Oudelaan",
    "price": 429000,
    "address": "6605 SG Wijchen (Oudelaan)",
    "size": 50.0,
    "energy_label": "Onbekend",
    "garden_terrace": "Nee",
    "image_url": "https://casco-media-prod.global.ssl.fastly.net/listings/api/media/151f248f-2e9d-5150-a36f-befac57bd5ce/0a6f3bc1-37e0-5bd2-885d-3667925deb89?original_uri=https%3A%2F%2Fwww.hansjanssen.nl%2Fapp%2Fuploads%2Fsure%2Fmedia%2FWN102739%2FWN102739-191412-Oudelaan-2107-Wijchen-258597646.jpg?sig=342ce87c062c53a3758a84d9283285dd994b20bb6fbe67936e2c380f279ff234&width=600&auto=webp",
    "link": "https://www.pararius.nl/huis-te-koop/wijchen/151f248f/oudelaan",
    "provider": "Pararius",
    "date_scraped": "2026-01-10"
  },
  {
    "title": "Houtsnijdershorst 634",
    "price": 395000,
    "address": "7328 WN Apeldoorn (Matenhorst)",
    "size": 50.0,
    "energy_label": "Onbekend",
    "garden_terrace": "Nee",
    "image_url": "https://casco-media-prod.global.ssl.fastly.net/9d04e4f7-ab8f-592c-a3b2-f4bc64bbcef7/ca5f7904fbf303ca092c869bef16004b.jpg?width=600&auto=webp",
    "link": "https://www.pararius.nl/huis-te-koop/apeldoorn/9d04e4f7/houtsnijdershorst",
    "provider": "Pararius",
    "date_scraped": "2026-01-10"
  },
  {
    "title": "Laureijnestraat",
    "price": 289000,
    "address": "4553 BW Philippine (Kern Philippine)",
    "size": 50.0,
    "energy_label": "Onbekend",
    "garden_terrace": "Nee",
    "image_url": "https://casco-media-prod.global.ssl.fastly.net/listings/api/media/e5910103-5628-5255-8357-c8f8e2035847/bbb4940f-281d-549e-8b05-77ef5a9b2fb3?original_uri=https%3A%2F%2Fimages.realworks.nl%2Fservlets%2Fimages%2Fmedia.objectmedia%2F258674404.webp%3Fcheck%3Dsha256%253A2fd706a6d0e8b21ff5088d03cb7faefa2d21f19a6a62b93d4e21406ae51918d8%26resize%3D4%26selected%3D258674404%23foto258674404?sig=dacc2722df0743181bd2de971575c2dfd1812dc6f4d5a1e089375aeec50c7fe5&width=600&auto=webp",
    "link": "https://www.pararius.nl/huis-te-koop/philippine/e5910103/laureijnestraat",
    "provider": "Pararius",
    "date_scraped": "2026-01-10"
  },
  {
    "title": "Luit",
    "price": 369000,
    "address": "8265 RW Kampen (De Maten)",
    "size": 50.0,
    "energy_label": "Onbekend",
    "garden_terrace": "Nee",
    "image_url": "https://casco-media-prod.global.ssl.fastly.net/listings/api/media/8c79ad3b-8af1-58e5-9c9c-bf4db5f50c8b/a71d7811-89dd-52f8-ba1a-a5faa456934d?original_uri=https%3A%2F%2Fimages.realworks.nl%2Fservlets%2Fimages%2Fmedia.objectmedia%2F257709674.webp%3Fcheck%3Dsha256%253Ab8864346355c44f5b80510ad3b137ad720cb6dd3a7717a742816a1a410ec5bac%26resize%3D4%26selected%3D257709674%23foto257709674?sig=594cae5e5de824e7fc3b8842abe646107e72ee5b5c0d652eb40c5bb96b264321&width=600&auto=webp",
    "link": "https://www.pararius.nl/huis-te-koop/kampen/8c79ad3b/luit",
    "provider": "Pararius",
    "date_scraped": "2026-01-10"
  },
  {
    "title": "Pastoor Meriusstraat",
    "price": 375000,
    "address": "1715 VG Spanbroek (Spanbroekerweg Kern)",
    "size": 50.0,
    "energy_label": "Onbekend",
    "garden_terrace": "Nee",
    "image_url": "https://casco-media-prod.global.ssl.fastly.net/listings/api/media/f80bfe7b-4ff9-5506-9fc1-5cf529af4d97/8c2f9655-4a7d-5f5d-806d-e4156722824a?original_uri=https%3A%2F%2Fimages.realworks.nl%2Fservlets%2Fimages%2Fmedia.objectmedia%2F258970076.webp%3Fcheck%3Dsha256%253A801ee9a0f42254de81de7fb4a5f24527ec4f640e075794d6d1efd49635a51b6f%26resize%3D4%26selected%3D258970076%23foto258970076?sig=f6055d0461edc9e055ee21c15228d40a27b73b25dd470ac6552e4784ca650681&width=600&auto=webp",
    "link": "https://www.pararius.nl/huis-te-koop/spanbroek/f80bfe7b/pastoor-meriusstraat",
    "provider": "Pararius",
    "date_scraped": "2026-01-10"
  },
  {
    "title": "Rietbeek 11",
    "price": 359000,
    "address": "6166 GT Geleen (Oud-Geleen en Haesselderveld)",
    "size": 50.0,
    "energy_label": "Onbekend",
    "garden_terrace": "Nee",
    "image_url": "https://casco-media-prod.global.ssl.fastly.net/793b7dc0-87a5-5bf4-9b79-607ab6910afb/4afbcb0affafab197849289db9a9336c.jpg?width=600&auto=webp",
    "link": "https://www.pararius.nl/huis-te-koop/geleen/793b7dc0/rietbeek",
    "provider": "Pararius",
    "date_scraped": "2026-01-10"
  },
  {
    "title": "Kemphaan",
    "price": 445000,
    "address": "5508 LD Veldhoven (De Kelen)",
    "size": 50.0,
    "energy_label": "Onbekend",
    "garden_terrace": "Nee",
    "image_url": "https://casco-media-prod.global.ssl.fastly.net/listings/api/media/e170bf2e-b52b-5e0c-ae6d-ea65963aa422/525d43f0-854d-5d0b-9825-afd46bec7111?original_uri=https%3A%2F%2Fimages.realworks.nl%2Fservlets%2Fimages%2Fmedia.objectmedia%2F258549896.webp%3Fcheck%3Dsha256%253Abd543bd0bf3a4646d59714ba2dc7150893978450f65ce9ef82c19caca014ea86%26resize%3D4%26selected%3D258549896%23foto258549896?sig=054c92f26b1ca424b96c692d5f342e0e7c211d8aeb092cf2e5e1afc93c7a6f87&width=600&auto=webp",
    "link": "https://www.pararius.nl/huis-te-koop/veldhoven/e170bf2e/kemphaan",
    "provider": "Pararius",
    "date_scraped": "2026-01-10"
  },
  {
    "title": "De Kamp 2",
    "price": 337500,
    "address": "6566 HC Millingen aan de Rijn (Millingen aan de Rijn-West)",
    "size": 50.0,
    "energy_label": "Onbekend",
    "garden_terrace": "Nee",
    "image_url": "https://casco-media-prod.global.ssl.fastly.net/ae5cbef1-7af6-5b32-8b7d-961a8a0b0827/97bcb2fdb006b4dd71e75e24b1edff44.jpg?width=600&auto=webp",
    "link": "https://www.pararius.nl/huis-te-koop/millingen-aan-de-rijn/ae5cbef1/de-kamp",
    "provider": "Pararius",
    "date_scraped": "2026-01-10"
  },
  {
    "title": "Gebroeders Fodorstraat",
    "price": 439000,
    "address": "5913 XM Venlo (De Tichelarij)",
    "size": 50.0,
    "energy_label": "Onbekend",
    "garden_terrace": "Nee",
    "image_url": "https://casco-media-prod.global.ssl.fastly.net/listings/api/media/be36fd32-0824-51b8-9949-46bbc3491e65/56a1dd00-31b9-5575-a0da-524a1b5f4142?original_uri=https%3A%2F%2Fimages.realworks.nl%2Fservlets%2Fimages%2Fmedia.objectmedia%2F258584084.webp%3Fcheck%3Dsha256%253A66217c025b965ded0394bf85136b8e6704e246aa0d249d9d682792391343ca00%26resize%3D4%26selected%3D258584084%23foto258584084?sig=a7e91bd33baac5bb910c474bfa1b70467466c7319db36c76a7b25ba4dcbb886b&width=600&auto=webp",
    "link": "https://www.pararius.nl/huis-te-koop/venlo/be36fd32/gebroeders-fodorstraat",
    "provider": "Pararius",
    "date_scraped": "2026-01-10"
  },
  {
    "title": "de Bongerd 6",
    "price": 349000,
    "address": "7251 CD Vorden (Vorden)",
    "size": 50.0,
    "energy_label": "Onbekend",
    "garden_terrace": "Nee",
    "image_url": "https://casco-media-prod.global.ssl.fastly.net/1d5e30f6-adfb-5a18-9d22-53da783b4c31/c09d39bf7abc2919b542fe65ee4cfea8.jpg?width=600&auto=webp",
    "link": "https://www.pararius.nl/huis-te-koop/vorden/1d5e30f6/de-bongerd",
    "provider": "Pararius",
    "date_scraped": "2026-01-10"
  },
  {
    "title": "Kuukven 12",
    "price": 350000,
    "address": "5991 NK Baarlo (Bong)",
    "size": 50.0,
    "energy_label": "Onbekend",
    "garden_terrace": "Nee",
    "image_url": "https://casco-media-prod.global.ssl.fastly.net/45865392-41c6-51b6-9f7a-79694e80ca71/a38f20470a9db0cd24c73c82f4d6a62a.jpg?width=600&auto=webp",
    "link": "https://www.pararius.nl/huis-te-koop/baarlo-lb/45865392/kuukven",
    "provider": "Pararius",
    "date_scraped": "2026-01-10"
  },
  {
    "title": "Otello",
    "price": 450000,
    "address": "8265 TD Kampen (De Maten)",
    "size": 50.0,
    "energy_label": "Onbekend",
    "garden_terrace": "Nee",
    "image_url": "https://casco-media-prod.global.ssl.fastly.net/listings/api/media/c14c43a3-5241-560b-8d04-a2664dbe1269/78da5a91-3660-578c-b5b9-47013444f5c2?original_uri=https%3A%2F%2Fimages.realworks.nl%2Fservlets%2Fimages%2Fmedia.objectmedia%2F258775204.webp%3Fcheck%3Dsha256%253Ab96b1f3cdc14bceed520da7538d4fd1ebbc948fd7dd42e78e7eb334adea946df%26resize%3D4%26selected%3D258775204%23foto258775204?sig=61095d9bc6bcac3bba2163a2776255d88a05deb6ea9adc81241bea621394bf30&width=600&auto=webp",
    "link": "https://www.pararius.nl/huis-te-koop/kampen/c14c43a3/otello",
    "provider": "Pararius",
    "date_scraped": "2026-01-10"
  },
  {
    "title": "Torenmolen 12",
    "price": 365000,
    "address": "1444 GE Purmerend (Molenkoog)",
    "size": 50.0,
    "energy_label": "Onbekend",
    "garden_terrace": "Nee",
    "image_url": "https://casco-media-prod.global.ssl.fastly.net/d03b540b-0b85-5f8f-906e-1450a9081931/4c544bc53511992e60f9c1592e43fdc2.jpg?width=600&auto=webp",
    "link": "https://www.pararius.nl/huis-te-koop/purmerend/d03b540b/torenmolen",
    "provider": "Pararius",
    "date_scraped": "2026-01-10"
  },
  {
    "title": "Slingerlandstraat 25",
    "price": 450000,
    "address": "4231 AD Meerkerk (Meerkerk-Noord)",
    "size": 50.0,
    "energy_label": "Onbekend",
    "garden_terrace": "Nee",
    "image_url": "https://casco-media-prod.global.ssl.fastly.net/12baa102-f68e-5721-9cb1-fc82abc18bae/88f4e88c2cf3eff1ff88915ca4d339bd.png?width=600&auto=webp",
    "link": "https://www.pararius.nl/huis-te-koop/meerkerk/12baa102/slingerlandstraat",
    "provider": "Pararius",
    "date_scraped": "2026-01-10"
  },
  {
    "title": "Pres J.F. Kennedystraat 20",
    "price": 359000,
    "address": "6286 BG Wittem (Verspreide huizen)",
    "size": 50.0,
    "energy_label": "Onbekend",
    "garden_terrace": "Nee",
    "image_url": "https://casco-media-prod.global.ssl.fastly.net/6fbb3100-256b-5d62-81ab-e24bbcc19130/0eaf674a7969edf507fc69a533fee512.jpg?width=600&auto=webp",
    "link": "https://www.pararius.nl/huis-te-koop/wittem/6fbb3100/pres-j-f-kennedystraat",
    "provider": "Pararius",
    "date_scraped": "2026-01-10"
  },
  {
    "title": "Sam van Houtenstraat",
    "price": 350000,
    "address": "1067 JK Amsterdam (Geuzenveld)",
    "size": 50.0,
    "energy_label": "Onbekend",
    "garden_terrace": "Nee",
    "image_url": "https://casco-media-prod.global.ssl.fastly.net/listings/api/media/507b5b40-e092-5618-810a-84a4256af5ba/74d535fd-3af9-54bf-bc71-3bf9b399d0e4?original_uri=https%3A%2F%2Fimages.realworks.nl%2Fservlets%2Fimages%2Fmedia.objectmedia%2F258571908.webp%3Fcheck%3Dsha256%253A2d2105d63f754d66fbfca4ec3a601f9bcc0847f5d15f2e8b7a9f95c2aa5bfeee%26resize%3D4%26selected%3D258571908%23foto258571908?sig=d1c9d560ea9c6cd2c9a39efc2eebff6b653587adcb7c449e221244a82516fff6&width=600&auto=webp",
    "link": "https://www.pararius.nl/appartement-te-koop/amsterdam/507b5b40/sam-van-houtenstraat",
    "provider": "Pararius",
    "date_scraped": "2026-01-10"
  },
  {
    "title": "Donatusstraat 24",
    "price": 299000,
    "address": "6361 TR Nuth (Nuth)",
    "size": 50.0,
    "energy_label": "Onbekend",
    "garden_terrace": "Nee",
    "image_url": "https://casco-media-prod.global.ssl.fastly.net/b98e94d7-c2a6-5184-bdd3-9e3b1a35da1b/abdea979cfa7957fe72c80f6e421a400.jpg?width=600&auto=webp",
    "link": "https://www.pararius.nl/huis-te-koop/nuth/b98e94d7/donatusstraat",
    "provider": "Pararius",
    "date_scraped": "2026-01-10"
  },
  {
    "title": "Escudo 47",
    "price": 400000,
    "address": "8253 ET Dronten (De Munten)",
    "size": 50.0,
    "energy_label": "Onbekend",
    "garden_terrace": "Nee",
    "image_url": "https://casco-media-prod.global.ssl.fastly.net/6e7f341d-c40c-512e-9c62-337af97328d8/103d1dcdbe92283c3478d30407d37e0d.jpg?width=600&auto=webp",
    "link": "https://www.pararius.nl/huis-te-koop/dronten/6e7f341d/escudo",
    "provider": "Pararius",
    "date_scraped": "2026-01-10"
  },
  {
    "title": "Pinglestraat",
    "price": 375000,
    "address": "8251 VM Dronten (De Landstreken)",
    "size": 50.0,
    "energy_label": "Onbekend",
    "garden_terrace": "Nee",
    "image_url": "https://casco-media-prod.global.ssl.fastly.net/listings/api/media/1b6b4488-6298-591d-9c14-21dd4801255e/0a66479b-ebd3-5fe4-932b-f8466d83e695?original_uri=https%3A%2F%2Fwww.vanderlinden.nl%2Fmedia_bb%2Fthumbs%2F1200x800%2F2571848.jpg?sig=94f4d0535932297cbbb51fa104397750e0cffab611bddc86c96099c9551d5e49&width=600&auto=webp",
    "link": "https://www.pararius.nl/huis-te-koop/dronten/1b6b4488/pinglestraat",
    "provider": "Pararius",
    "date_scraped": "2026-01-10"
  },
  {
    "title": "Pluimzegge 12",
    "price": 430000,
    "address": "2957 RG Nieuw-Lekkerland (Nieuw-Lekkerland-Dorp)",
    "size": 50.0,
    "energy_label": "Onbekend",
    "garden_terrace": "Nee",
    "image_url": "https://casco-media-prod.global.ssl.fastly.net/ca0e1915-f96a-539c-a696-0deb26d5518e/b8aa9e9752a3f9d444e0b4bb78320f8e.jpg?width=600&auto=webp",
    "link": "https://www.pararius.nl/huis-te-koop/nieuw-lekkerland/ca0e1915/pluimzegge",
    "provider": "Pararius",
    "date_scraped": "2026-01-10"
  },
  {
    "title": "Wallensgaard 1",
    "price": 339000,
    "address": "6227 GM Maastricht (Heer)",
    "size": 50.0,
    "energy_label": "Onbekend",
    "garden_terrace": "Nee",
    "image_url": "https://casco-media-prod.global.ssl.fastly.net/b6bd9b56-6a46-58b6-babb-4bcb9cbe20f3/7d7c4d7bd6ce7f80c8847433595d41ee.jpg?width=600&auto=webp",
    "link": "https://www.pararius.nl/huis-te-koop/maastricht/b6bd9b56/wallensgaard",
    "provider": "Pararius",
    "date_scraped": "2026-01-10"
  },
  {
    "title": "Kalkbranderstraat 15",
    "price": 349000,
    "address": "8043 BG Zwolle (Schoonhorst)",
    "size": 50.0,
    "energy_label": "Onbekend",
    "garden_terrace": "Nee",
    "image_url": "https://casco-media-prod.global.ssl.fastly.net/5f551193-7882-565c-880d-1c2f7c731a11/1a4683b9805764ed3504155e85adf7ae.jpg?width=600&auto=webp",
    "link": "https://www.pararius.nl/huis-te-koop/zwolle/5f551193/kalkbranderstraat",
    "provider": "Pararius",
    "date_scraped": "2026-01-10"
  }
]